{
    "able": 1,
    "abode": 1,
    "abraham": 1,
    "accepted": 1,
    "according": 1,
    "ached": 1,
    "act": 1,
    "acta": 2,
    "acts": 1,
    "ad": 2,
    "admitted": 1,
    "admonish": 1,
    "admonished": 4,
    "admonitions": 2,
    "afresh": 1,
    "afterwards": 1,
    "albeit": 1,
    "allmerciful": 1,
    "allowed": 1,
    "alone": 1,
    "already": 3,
    "also": 5,
    "although": 2,
    "altogether": 1,
    "amen": 2,
    "amid": 1,
    "angel": 1,
    "angels": 2,
    "anger": 1,
    "angered": 1,
    "anguish": 1,
    "another": 5,
    "answer": 3,
    "answered": 6,
    "anywhere": 1,
    "apocal": 2,
    "apparitio": 1,
    "appear": 1,
    "appeared": 2,
    "arm": 1,
    "arms": 1,
    "art": 5,
    "articles": 1,
    "articulus": 1,
    "ashamed": 1,
    "aside": 1,
    "asked": 2,
    "aspen": 1,
    "assuredly": 1,
    "auctores": 1,
    "aught": 2,
    "augusti": 1,
    "avail": 1,
    "await": 1,
    "awaits": 1,
    "awarded": 1,
    "away": 6,
    "back": 6,
    "backsliding": 2,
    "backwards": 1,
    "bade": 6,
    "bag": 1,
    "bald": 1,
    "barefooted": 2,
    "barrel": 1,
    "bastard": 1,
    "bear": 2,
    "beasts": 2,
    "beat": 1,
    "become": 2,
    "began": 6,
    "begged": 1,
    "begging": 1,
    "begin": 2,
    "beginninga": 1,
    "behind": 2,
    "behold": 1,
    "believe": 1,
    "believed": 2,
    "believing": 1,
    "bench": 1,
    "benzensis": 4,
    "besought": 1,
    "better": 3,
    "bewitch": 2,
    "bible": 1,
    "bichlke": 1,
    "bidden": 1,
    "biehlke": 1,
    "bind": 2,
    "birth": 1,
    "bitterly": 1,
    "black": 4,
    "blackberries": 1,
    "blaspheming": 1,
    "blessed": 2,
    "blind": 2,
    "blinded": 1,
    "blood": 5,
    "blow": 1,
    "blushed": 1,
    "body": 4,
    "boiling": 2,
    "bond": 1,
    "bones": 1,
    "boots": 1,
    "born": 1,
    "borne": 1,
    "bound": 3,
    "bowed": 1,
    "breast": 1,
    "brewed": 1,
    "bride": 1,
    "brimstone": 5,
    "brought": 5,
    "brown": 1,
    "bubbling": 1,
    "burned": 2,
    "burneth": 1,
    "burning": 2,
    "burnt": 1,
    "burst": 1,
    "caldron": 4,
    "calf": 1,
    "call": 2,
    "called": 4,
    "calleth": 1,
    "calling": 1,
    "came": 5,
    "camerarius": 1,
    "cannot": 1,
    "care": 1,
    "carnally": 1,
    "carry": 1,
    "cast": 1,
    "castleyard": 1,
    "catch": 1,
    "caterpillars": 1,
    "cause": 2,
    "caused": 2,
    "ceiling": 1,
    "central": 3,
    "certainly": 1,
    "chains": 1,
    "chair": 2,
    "chairs": 1,
    "chalk": 1,
    "chamber": 4,
    "changeling": 1,
    "chapter": 1,
    "charge": 1,
    "charged": 1,
    "charm": 1,
    "cheeks": 2,
    "cheer": 1,
    "chief": 1,
    "child": 25,
    "choose": 1,
    "christ": 1,
    "christening": 1,
    "christian": 1,
    "christians": 1,
    "chron": 1,
    "church": 1,
    "cited": 1,
    "cloak": 1,
    "close": 1,
    "clothe": 1,
    "clothed": 1,
    "clout": 1,
    "coach": 1,
    "cold": 1,
    "come": 7,
    "coming": 1,
    "commandment": 1,
    "commissum": 1,
    "conceived": 1,
    "confess": 12,
    "confessed": 2,
    "confessholla": 1,
    "confession": 1,
    "conjured": 2,
    "conjuring": 1,
    "consider": 1,
    "considered": 1,
    "considering": 1,
    "constable": 19,
    "constructed": 1,
    "consul": 23,
    "contained": 1,
    "continued": 1,
    "corner": 3,
    "could": 8,
    "court": 22,
    "covered": 1,
    "cried": 4,
    "cries": 1,
    "crieth": 1,
    "crimes": 1,
    "crop": 1,
    "cross": 3,
    "crown": 1,
    "cruel": 1,
    "cry": 2,
    "crying": 1,
    "daemonis": 1,
    "darling": 1,
    "daughter": 8,
    "day": 6,
    "days": 2,
    "dead": 1,
    "deal": 1,
    "death": 3,
    "decent": 1,
    "declare": 1,
    "declared": 2,
    "deep": 2,
    "defensio": 3,
    "delay": 1,
    "delivered": 1,
    "deny": 1,
    "depart": 1,
    "departed": 1,
    "desist": 1,
    "despair": 1,
    "desperate": 1,
    "devil": 7,
    "devils": 1,
    "dipped": 1,
    "disciples": 1,
    "disidaemonia": 1,
    "distress": 1,
    "dog": 1,
    "dom": 26,
    "done": 4,
    "door": 3,
    "doubt": 1,
    "doubting": 1,
    "drew": 1,
    "drive": 1,
    "driven": 2,
    "drove": 1,
    "drum": 1,
    "drumming": 1,
    "dure": 1,
    "duty": 2,
    "dwell": 1,
    "dying": 3,
    "earth": 2,
    "eat": 1,
    "egkatelipes": 1,
    "eli": 2,
    "enough": 1,
    "ephesus": 2,
    "error": 1,
    "especially": 3,
    "et": 2,
    "etc": 1,
    "even": 1,
    "ever": 6,
    "every": 2,
    "evil": 1,
    "exceeding": 2,
    "excellent": 1,
    "executioner": 4,
    "expressly": 1,
    "extraordinary": 1,
    "eyes": 3,
    "face": 2,
    "faces": 1,
    "failed": 1,
    "faith": 1,
    "faithful": 1,
    "fall": 1,
    "fallen": 2,
    "fama": 1,
    "far": 2,
    "fast": 1,
    "father": 9,
    "fathers": 1,
    "feareth": 1,
    "fee": 1,
    "feet": 7,
    "fell": 5,
    "fellow": 2,
    "fetch": 1,
    "fiend": 3,
    "file": 1,
    "filthy": 1,
    "fingers": 1,
    "fire": 2,
    "firm": 1,
    "first": 8,
    "fish": 1,
    "five": 1,
    "flesh": 1,
    "fleshly": 1,
    "flock": 1,
    "floor": 1,
    "flung": 1,
    "follow": 1,
    "followed": 3,
    "follows": 3,
    "followsthat": 1,
    "folly": 1,
    "food": 1,
    "fool": 1,
    "foolish": 1,
    "foot": 1,
    "force": 1,
    "foretaste": 1,
    "forget": 1,
    "forsake": 1,
    "forte": 1,
    "forth": 3,
    "forthwith": 1,
    "forward": 2,
    "foul": 3,
    "found": 1,
    "fourteen": 1,
    "freely": 1,
    "freewill": 1,
    "fresh": 1,
    "fright": 1,
    "frighten": 1,
    "frog": 1,
    "front": 1,
    "frowned": 1,
    "fulfil": 1,
    "full": 1,
    "gal": 1,
    "garments": 1,
    "gave": 7,
    "ghost": 2,
    "giant": 1,
    "gift": 1,
    "give": 1,
    "given": 6,
    "gladly": 1,
    "glass": 1,
    "glee": 1,
    "glory": 2,
    "go": 6,
    "goat": 1,
    "god": 17,
    "gods": 1,
    "gone": 3,
    "good": 2,
    "goose": 2,
    "gooses": 1,
    "got": 1,
    "gout": 1,
    "gracious": 3,
    "granted": 1,
    "great": 1,
    "greatly": 2,
    "greek": 2,
    "greet": 1,
    "grew": 2,
    "grief": 1,
    "grieveth": 1,
    "grin": 1,
    "grinning": 1,
    "ground": 1,
    "growing": 1,
    "grumbled": 1,
    "guileless": 2,
    "gussy": 1,
    "hairs": 1,
    "hairy": 1,
    "ham": 1,
    "hand": 4,
    "hands": 7,
    "happen": 2,
    "hardly": 1,
    "harm": 2,
    "hast": 4,
    "hateful": 2,
    "hath": 3,
    "hatred": 1,
    "head": 4,
    "hear": 1,
    "heard": 6,
    "hearkened": 1,
    "heathens": 3,
    "heaved": 1,
    "heaven": 1,
    "heavenly": 1,
    "heavens": 1,
    "heavier": 1,
    "hedgehog": 1,
    "heeded": 1,
    "heeding": 1,
    "held": 3,
    "hell": 2,
    "hellhound": 3,
    "hellish": 2,
    "help": 5,
    "helped": 1,
    "hereat": 2,
    "hereby": 1,
    "hereupon": 16,
    "high": 3,
    "highest": 1,
    "hither": 1,
    "ho": 6,
    "hold": 1,
    "holy": 6,
    "home": 1,
    "honest": 1,
    "honour": 1,
    "honourable": 5,
    "hope": 2,
    "hoped": 1,
    "horns": 1,
    "hot": 1,
    "hourglass": 2,
    "house": 1,
    "housekeeper": 4,
    "howbeit": 2,
    "however": 2,
    "humbled": 1,
    "idolatrous": 1,
    "ii": 1,
    "iii": 1,
    "ill": 1,
    "illa": 1,
    "illustration": 1,
    "ilse": 1,
    "impatient": 1,
    "impudent": 3,
    "inasmuch": 2,
    "indeed": 4,
    "indicia": 1,
    "indictment": 1,
    "inflicted": 2,
    "inherit": 1,
    "innocence": 1,
    "innocent": 4,
    "ins": 1,
    "instead": 1,
    "instrumenta": 1,
    "intercessor": 1,
    "ipsam": 1,
    "israel": 1,
    "item": 6,
    "iuati": 1,
    "jer": 1,
    "john": 2,
    "joints": 1,
    "joys": 1,
    "judge": 1,
    "judges": 1,
    "judgment": 1,
    "judgmentchamber": 1,
    "jumped": 1,
    "keeping": 1,
    "kept": 1,
    "kicked": 1,
    "kindness": 2,
    "king": 1,
    "kingdom": 1,
    "knees": 4,
    "knew": 4,
    "know": 1,
    "knowest": 1,
    "known": 3,
    "ladder": 3,
    "laid": 3,
    "lake": 1,
    "lama": 1,
    "lamb": 3,
    "large": 1,
    "last": 6,
    "lastly": 2,
    "latter": 1,
    "laughed": 1,
    "laughter": 1,
    "lay": 3,
    "lead": 2,
    "leaf": 1,
    "leaning": 1,
    "least": 1,
    "leave": 1,
    "led": 3,
    "leg": 1,
    "legitima": 1,
    "less": 3,
    "let": 2,
    "liar": 1,
    "lie": 1,
    "lies": 2,
    "life": 1,
    "lift": 3,
    "lifted": 1,
    "light": 1,
    "like": 8,
    "likewise": 2,
    "list": 1,
    "little": 2,
    "lived": 2,
    "living": 1,
    "lizzie": 2,
    "lock": 2,
    "loins": 1,
    "long": 4,
    "longer": 2,
    "look": 3,
    "looked": 1,
    "loose": 1,
    "loosed": 1,
    "lord": 5,
    "loud": 1,
    "love": 3,
    "loved": 1,
    "lovely": 1,
    "luke": 1,
    "made": 3,
    "magistrates": 1,
    "maid": 3,
    "maiden": 1,
    "main": 1,
    "make": 5,
    "mala": 1,
    "maleficium": 1,
    "malum": 1,
    "man": 1,
    "manasseh": 1,
    "manner": 2,
    "many": 5,
    "mark": 2,
    "martyrs": 1,
    "mary": 6,
    "matchless": 2,
    "matter": 1,
    "may": 1,
    "mayest": 2,
    "mean": 1,
    "means": 1,
    "meant": 1,
    "meet": 1,
    "men": 2,
    "mensis": 1,
    "merciful": 3,
    "mercy": 1,
    "might": 3,
    "mine": 1,
    "minutes": 1,
    "misery": 1,
    "money": 1,
    "monte": 1,
    "morning": 1,
    "motioned": 1,
    "mou": 2,
    "mountain": 1,
    "moved": 1,
    "murderer": 1,
    "murmur": 1,
    "must": 9,
    "naked": 1,
    "name": 5,
    "namely": 1,
    "nasty": 1,
    "nay": 1,
    "nearly": 1,
    "neckerchief": 2,
    "needs": 1,
    "neighbors": 1,
    "neither": 1,
    "never": 7,
    "new": 2,
    "news": 2,
    "next": 5,
    "night": 2,
    "none": 1,
    "noon": 1,
    "nothing": 1,
    "nought": 2,
    "oft": 1,
    "often": 2,
    "oh": 3,
    "old": 13,
    "older": 1,
    "one": 7,
    "open": 1,
    "opened": 1,
    "orchard": 1,
    "order": 2,
    "ordered": 3,
    "ordinary": 1,
    "others": 1,
    "ought": 1,
    "outs": 1,
    "overcame": 1,
    "overcome": 2,
    "owned": 1,
    "paasch": 1,
    "pale": 1,
    "paramour": 1,
    "part": 3,
    "pass": 1,
    "passed": 1,
    "pastor": 4,
    "paul": 1,
    "peace": 2,
    "peeped": 1,
    "peine": 1,
    "perceived": 1,
    "picked": 1,
    "pile": 1,
    "pitch": 1,
    "pity": 4,
    "played": 1,
    "plucked": 1,
    "poor": 11,
    "pour": 1,
    "praegnantia": 1,
    "pray": 4,
    "prayed": 3,
    "prayer": 1,
    "presence": 1,
    "presently": 3,
    "principals": 1,
    "prison": 4,
    "promise": 2,
    "promised": 1,
    "promises": 1,
    "protest": 1,
    "protocollum": 1,
    "public\u00e8": 1,
    "pull": 1,
    "pulled": 2,
    "punishment": 1,
    "purpose": 1,
    "pushed": 1,
    "put": 7,
    "q": 13,
    "question": 4,
    "questioned": 1,
    "questions": 2,
    "quiet": 1,
    "quietly": 1,
    "quills": 2,
    "quite": 1,
    "r": 12,
    "rage": 1,
    "railing": 1,
    "raked": 1,
    "ran": 1,
    "rate": 1,
    "rather": 1,
    "ravening": 1,
    "rea": 2,
    "read": 4,
    "reading": 1,
    "ready": 1,
    "really": 1,
    "rebaptism": 1,
    "rebaptized": 2,
    "rebuked": 1,
    "receive": 1,
    "received": 3,
    "red": 3,
    "registered": 1,
    "rejoiced": 1,
    "relate": 1,
    "remained": 1,
    "remember": 5,
    "repent": 3,
    "repentance": 2,
    "replied": 1,
    "resigned": 1,
    "rest": 1,
    "return": 3,
    "reward": 1,
    "right": 4,
    "rind": 1,
    "rings": 1,
    "roast": 2,
    "rolled": 1,
    "roof": 1,
    "room": 5,
    "rose": 3,
    "rumor": 1,
    "run": 1,
    "sabachthani": 1,
    "said": 18,
    "saith": 2,
    "sake": 1,
    "salvation": 1,
    "sat": 5,
    "satan": 7,
    "satisfied": 1,
    "savage": 3,
    "save": 11,
    "saviour": 5,
    "saw": 1,
    "say": 2,
    "sayest": 1,
    "saying": 3,
    "scales": 1,
    "scarce": 2,
    "schweidler": 1,
    "scourged": 1,
    "screw": 1,
    "scriba": 1,
    "sea": 1,
    "second": 1,
    "seden": 1,
    "see": 5,
    "seeing": 9,
    "seen": 6,
    "seize": 2,
    "seized": 1,
    "send": 1,
    "sent": 4,
    "sentence": 2,
    "sentenced": 1,
    "set": 2,
    "severer": 1,
    "shall": 13,
    "shape": 4,
    "shepherd": 1,
    "sheriff": 7,
    "shift": 1,
    "shining": 1,
    "shook": 4,
    "shoot": 1,
    "shorn": 1,
    "shoulders": 1,
    "shouted": 1,
    "show": 1,
    "showed": 1,
    "shuddered": 2,
    "sickness": 1,
    "sides": 1,
    "sigh": 1,
    "sighed": 1,
    "sight": 1,
    "sign": 2,
    "signify": 1,
    "silken": 2,
    "single": 2,
    "sister": 3,
    "sit": 1,
    "sitting": 1,
    "six": 1,
    "skin": 1,
    "skullcap": 1,
    "slaughterhouse": 1,
    "smoked": 1,
    "sneers": 1,
    "snowwhite": 1,
    "sob": 1,
    "sobs": 1,
    "sometimes": 1,
    "son": 2,
    "soon": 4,
    "sooner": 1,
    "sorcerers": 1,
    "sorrow": 1,
    "soul": 4,
    "spanish": 1,
    "spared": 2,
    "speak": 3,
    "spell": 1,
    "spirits": 1,
    "spirt": 1,
    "spirted": 1,
    "spoken": 2,
    "sponsors": 1,
    "spots": 1,
    "sprang": 1,
    "squeezest": 1,
    "st": 1,
    "stained": 1,
    "stake": 1,
    "stand": 4,
    "started": 1,
    "stay": 2,
    "steadfast": 1,
    "steadfastly": 1,
    "stepped": 1,
    "steps": 1,
    "still": 6,
    "stood": 3,
    "storm": 2,
    "straightway": 2,
    "stray": 1,
    "stretch": 1,
    "strip": 1,
    "stroked": 1,
    "stronger": 1,
    "struggled": 1,
    "stubborn": 4,
    "subjected": 1,
    "suffer": 3,
    "suffered": 2,
    "suffice": 1,
    "sufficientia": 1,
    "supposing": 1,
    "surplice": 1,
    "sweden": 1,
    "sweet": 1,
    "swore": 1,
    "swound": 2,
    "syndicus": 2,
    "table": 1,
    "tables": 1,
    "take": 2,
    "taken": 1,
    "tall": 4,
    "tarry": 1,
    "taught": 1,
    "tear": 2,
    "tears": 5,
    "tell": 1,
    "ten": 1,
    "terrible": 2,
    "terror": 1,
    "testament": 2,
    "testes": 1,
    "th": 1,
    "thanked": 1,
    "thee": 18,
    "thence": 1,
    "thereat": 1,
    "thereby": 2,
    "therefore": 5,
    "thereof": 1,
    "thereon": 1,
    "thing": 1,
    "things": 1,
    "think": 1,
    "thorns": 1,
    "thou": 21,
    "though": 2,
    "threatened": 1,
    "threw": 2,
    "throw": 1,
    "thrust": 1,
    "thumbscrew": 3,
    "thursday": 1,
    "thus": 5,
    "thy": 18,
    "thyself": 1,
    "tickle": 1,
    "tickling": 1,
    "tied": 1,
    "till": 1,
    "time": 2,
    "tips": 1,
    "today": 1,
    "together": 1,
    "told": 1,
    "took": 1,
    "top": 1,
    "torches": 2,
    "tore": 2,
    "torment": 2,
    "tormented": 3,
    "torments": 1,
    "torn": 1,
    "torturam": 1,
    "torture": 5,
    "torturebench": 2,
    "torturechamber": 2,
    "tortureshift": 2,
    "touched": 1,
    "touching": 1,
    "toward": 2,
    "towards": 1,
    "trembled": 1,
    "trembling": 1,
    "truth": 4,
    "try": 1,
    "turned": 2,
    "twentythird": 1,
    "twisted": 1,
    "two": 6,
    "unbound": 2,
    "understand": 1,
    "understood": 1,
    "undress": 1,
    "uneasily": 1,
    "unrighteous": 1,
    "unto": 6,
    "upon": 24,
    "us": 7,
    "use": 1,
    "v": 1,
    "varlet": 1,
    "vault": 6,
    "veil": 1,
    "vein": 1,
    "viii": 1,
    "vile": 1,
    "village": 1,
    "virgin": 2,
    "virgins": 1,
    "voice": 4,
    "wait": 1,
    "walked": 1,
    "walking": 1,
    "wall": 1,
    "wanting": 2,
    "wanton": 1,
    "warlocks": 1,
    "watch": 1,
    "way": 1,
    "weak": 1,
    "wedge": 1,
    "weep": 2,
    "weeping": 1,
    "well": 3,
    "went": 9,
    "wert": 1,
    "whatsoeer": 1,
    "whence": 2,
    "whereat": 3,
    "wherefore": 6,
    "wherefrom": 1,
    "wherein": 2,
    "whereof": 1,
    "whereon": 2,
    "whereupon": 9,
    "whether": 11,
    "white": 2,
    "whole": 3,
    "wife": 3,
    "wilt": 6,
    "windows": 1,
    "wing": 1,
    "wise": 1,
    "wish": 1,
    "wit": 2,
    "witch": 1,
    "witchcraft": 2,
    "witches": 1,
    "within": 2,
    "without": 4,
    "wolf": 1,
    "woman": 2,
    "women": 6,
    "wondrous": 1,
    "wont": 2,
    "word": 5,
    "words": 5,
    "wore": 2,
    "worn": 1,
    "worshipful": 10,
    "worthy": 2,
    "would": 24,
    "wounds": 1,
    "wrath": 1,
    "wretched": 3,
    "wroth": 2,
    "xiii": 2,
    "xix": 1,
    "xxi": 1,
    "xxxiii": 1,
    "ye": 6,
    "year": 1,
    "years": 1,
    "yes": 2,
    "yet": 4,
    "yore": 1,
    "young": 1
}
