{
    "able": 2,
    "abounded": 1,
    "absurdest": 1,
    "abundance": 1,
    "accepted": 1,
    "according": 3,
    "account": 11,
    "accounts": 3,
    "accumulation": 1,
    "accurate": 1,
    "accusation": 2,
    "accusations": 2,
    "accused": 21,
    "acquired": 1,
    "acquit": 1,
    "acquittal": 3,
    "acquittals": 1,
    "acquittalsthe": 1,
    "acquitted": 3,
    "acted": 1,
    "action": 2,
    "actions": 1,
    "active": 1,
    "activities": 1,
    "activity": 1,
    "ad": 1,
    "added": 1,
    "addressed": 1,
    "adds": 1,
    "admission": 1,
    "admits": 1,
    "admitted": 1,
    "adverse": 1,
    "affair": 9,
    "affirmed": 1,
    "afflicted": 2,
    "afraid": 1,
    "afterwards": 4,
    "agency": 1,
    "aggressive": 1,
    "ago": 1,
    "agreed": 1,
    "alarm": 1,
    "alarmed": 1,
    "alas": 1,
    "alderman": 1,
    "alive": 2,
    "allow": 1,
    "allowed": 2,
    "almost": 3,
    "alms": 1,
    "alone": 1,
    "along": 2,
    "already": 1,
    "also": 6,
    "alter": 1,
    "altered": 1,
    "although": 2,
    "altogether": 2,
    "always": 4,
    "amazement": 1,
    "among": 7,
    "amy": 3,
    "anent": 1,
    "anglia": 1,
    "angry": 1,
    "ann": 9,
    "annals": 2,
    "annoyed": 1,
    "another": 8,
    "answered": 1,
    "answers": 1,
    "anticipate": 1,
    "anyone": 1,
    "anything": 1,
    "aplenty": 1,
    "apology": 1,
    "apothecaries": 1,
    "apparitions": 2,
    "appearances": 1,
    "appeared": 1,
    "appears": 1,
    "appendix": 1,
    "application": 2,
    "appoint": 1,
    "appointed": 1,
    "arbour": 1,
    "archaeological": 1,
    "archdefender": 1,
    "archer": 5,
    "arm": 3,
    "armed": 1,
    "armstrong": 1,
    "armstrongs": 1,
    "around": 1,
    "arraigned": 3,
    "arrived": 1,
    "arts": 2,
    "ascribes": 1,
    "ashes": 1,
    "ask": 2,
    "asked": 2,
    "assign": 1,
    "assistance": 1,
    "assisted": 1,
    "assize": 3,
    "assizes": 6,
    "associate": 1,
    "assumed": 1,
    "astrologers": 1,
    "attached": 1,
    "attack": 3,
    "attacked": 1,
    "attitude": 1,
    "attracted": 1,
    "author": 1,
    "authority": 2,
    "authors": 1,
    "avoided": 2,
    "away": 3,
    "back": 2,
    "backing": 1,
    "bad": 1,
    "baffled": 1,
    "bail": 1,
    "bailey": 1,
    "baptists": 3,
    "bar": 3,
    "barbers": 1,
    "barns": 1,
    "baron": 6,
    "barrenness": 1,
    "barring": 1,
    "barrow": 4,
    "batches": 1,
    "bear": 2,
    "beaumont": 1,
    "became": 2,
    "become": 4,
    "becoming": 2,
    "bed": 1,
    "beds": 1,
    "bee": 2,
    "befallen": 1,
    "began": 2,
    "beggar": 1,
    "beggars": 1,
    "begged": 1,
    "beginning": 3,
    "behaviour": 1,
    "behind": 3,
    "beings": 1,
    "belief": 3,
    "believe": 1,
    "believed": 3,
    "believer": 1,
    "believeth": 1,
    "belongs": 1,
    "bench": 2,
    "bent": 1,
    "berkhampstead": 1,
    "best": 1,
    "betrays": 1,
    "bewitch": 1,
    "bewitched": 10,
    "bewitching": 3,
    "bewitchment": 1,
    "bible": 1,
    "bickering": 1,
    "bishop": 1,
    "bits": 1,
    "blood": 1,
    "blow": 1,
    "blue": 1,
    "boasted": 1,
    "body": 6,
    "bold": 1,
    "bones": 1,
    "book": 1,
    "borough": 1,
    "boy": 6,
    "boys": 1,
    "bradford": 1,
    "breath": 1,
    "bridled": 1,
    "briefly": 1,
    "brighouse": 1,
    "brightling": 1,
    "brilliant": 1,
    "bring": 1,
    "broke": 1,
    "broken": 1,
    "brood": 1,
    "brought": 15,
    "browne": 3,
    "brownes": 2,
    "bull": 1,
    "burneda": 1,
    "burnet": 1,
    "burning": 1,
    "bury": 5,
    "bush": 2,
    "buts": 1,
    "butts": 1,
    "bystanders": 1,
    "cal": 1,
    "call": 1,
    "called": 9,
    "calming": 1,
    "cambridge": 3,
    "came": 8,
    "campbell": 1,
    "cannot": 4,
    "canterbury": 1,
    "capable": 1,
    "care": 1,
    "career": 1,
    "careful": 3,
    "carried": 1,
    "carry": 1,
    "carryed": 1,
    "case": 22,
    "cases": 15,
    "cast": 1,
    "castle": 1,
    "casual": 1,
    "cat": 3,
    "catechized": 1,
    "catholics": 1,
    "cats": 2,
    "cause": 1,
    "caused": 2,
    "caution": 1,
    "ceased": 2,
    "celebrated": 1,
    "celebrates": 1,
    "censured": 1,
    "centre": 3,
    "century": 9,
    "certain": 6,
    "certainly": 1,
    "chairs": 1,
    "chamber": 1,
    "chance": 3,
    "chances": 1,
    "change": 1,
    "changes": 1,
    "chaplain": 1,
    "chapter": 4,
    "chapters": 1,
    "character": 2,
    "characterized": 1,
    "charge": 4,
    "charged": 1,
    "charges": 5,
    "charles": 7,
    "charmers": 1,
    "chase": 1,
    "chased": 1,
    "chetham": 1,
    "chief": 13,
    "child": 8,
    "children": 10,
    "childrens": 1,
    "childs": 1,
    "chimney": 2,
    "choak": 1,
    "circuit": 1,
    "circuiti": 1,
    "circumstance": 1,
    "circumstances": 2,
    "cit": 7,
    "cited": 1,
    "cites": 1,
    "city": 1,
    "civil": 4,
    "claim": 1,
    "claimed": 1,
    "claims": 1,
    "class": 1,
    "classed": 1,
    "clear": 2,
    "clergymen": 1,
    "clinch": 1,
    "close": 4,
    "closed": 1,
    "closely": 1,
    "clumsy": 1,
    "clutches": 1,
    "coherent": 1,
    "coincident": 1,
    "colleague": 3,
    "colleagues": 2,
    "collected": 1,
    "collection": 1,
    "collections": 1,
    "come": 9,
    "comedy": 1,
    "comes": 1,
    "comethat": 1,
    "comm": 1,
    "comment": 3,
    "commit": 1,
    "commitments": 1,
    "committed": 2,
    "committee": 3,
    "committees": 1,
    "common": 2,
    "commonplace": 1,
    "commonwealth": 1,
    "community": 1,
    "communitys": 1,
    "companions": 1,
    "compare": 1,
    "compelled": 1,
    "competition": 1,
    "competitors": 1,
    "complaint": 2,
    "complete": 1,
    "composed": 1,
    "compute": 1,
    "conceived": 1,
    "concern": 1,
    "concernd": 1,
    "concerned": 3,
    "conclusion": 2,
    "condemn": 1,
    "condemnation": 1,
    "condemned": 3,
    "condemning": 1,
    "conducted": 1,
    "confederacy": 1,
    "confess": 2,
    "confessed": 3,
    "confession": 3,
    "confessions": 8,
    "confidence": 1,
    "confident": 1,
    "confined": 1,
    "confirmed": 2,
    "conjurer": 1,
    "connect": 1,
    "connected": 1,
    "connection": 5,
    "consequence": 1,
    "consider": 1,
    "considerable": 1,
    "considered": 3,
    "consisted": 1,
    "constant": 2,
    "constituted": 1,
    "constituting": 1,
    "constrained": 1,
    "consulted": 3,
    "contact": 1,
    "contemporaneous": 1,
    "contemporaries": 1,
    "contemporary": 1,
    "continued": 1,
    "contracting": 1,
    "contradiction": 1,
    "contrary": 2,
    "controversy": 1,
    "conventicle": 1,
    "conventicles": 2,
    "conversation": 1,
    "conviction": 2,
    "convinced": 1,
    "convulsed": 1,
    "convulsive": 2,
    "cooperating": 1,
    "cornwall": 4,
    "correspondence": 1,
    "cost": 1,
    "could": 9,
    "council": 1,
    "counsayle": 1,
    "counties": 4,
    "county": 6,
    "course": 4,
    "court": 18,
    "courts": 10,
    "covered": 1,
    "coworkers": 1,
    "cox": 5,
    "crackling": 1,
    "creatures": 3,
    "credited": 1,
    "credulous": 2,
    "cried": 2,
    "crime": 1,
    "crimes": 6,
    "criminal": 1,
    "criticism": 3,
    "cromwell": 1,
    "cromwells": 1,
    "crooked": 1,
    "crown": 1,
    "crump": 3,
    "crush": 1,
    "cruthers": 1,
    "cryed": 1,
    "cullender": 1,
    "cure": 2,
    "cured": 1,
    "curing": 1,
    "curious": 1,
    "curiously": 1,
    "current": 2,
    "cursed": 1,
    "custody": 1,
    "cut": 3,
    "daimonomageia": 2,
    "damning": 2,
    "danced": 1,
    "dances": 1,
    "dancing": 2,
    "danger": 1,
    "dared": 2,
    "darrels": 1,
    "date": 1,
    "daughter": 1,
    "day": 1,
    "days": 4,
    "dead": 2,
    "deal": 1,
    "dealing": 2,
    "dealt": 1,
    "death": 5,
    "decade": 1,
    "deceived": 1,
    "decided": 1,
    "decision": 4,
    "decisions": 5,
    "declare": 1,
    "declared": 4,
    "declares": 1,
    "deduced": 1,
    "deemed": 2,
    "defence": 1,
    "defendant": 1,
    "definite": 1,
    "degree": 2,
    "delighted": 1,
    "deliverance": 2,
    "delivery": 1,
    "denmark": 1,
    "departure": 1,
    "depended": 1,
    "depositions": 9,
    "deriders": 1,
    "derision": 1,
    "derive": 1,
    "described": 1,
    "design": 1,
    "designate": 1,
    "desire": 1,
    "detailed": 1,
    "details": 6,
    "detect": 1,
    "developed": 3,
    "devil": 6,
    "devils": 2,
    "devon": 1,
    "devonshire": 4,
    "diagnosis": 1,
    "diaries": 1,
    "diary": 2,
    "die": 1,
    "difference": 1,
    "differences": 1,
    "different": 4,
    "difficulties": 1,
    "difficulty": 1,
    "diligently": 1,
    "directed": 1,
    "direction": 1,
    "directions": 1,
    "disbelievers": 1,
    "discernible": 1,
    "dischargd": 1,
    "discharged": 1,
    "discover": 1,
    "discovered": 3,
    "discoverers": 1,
    "discovery": 1,
    "discussions": 1,
    "disease": 1,
    "diseases": 1,
    "dismissed": 3,
    "dispirited": 3,
    "disreputable": 1,
    "dissatisfied": 1,
    "dissenters": 2,
    "dissertation": 1,
    "distinct": 1,
    "distinctions": 1,
    "distinctly": 2,
    "distortion": 1,
    "distributed": 1,
    "disturbed": 1,
    "doctor": 5,
    "doctorand": 1,
    "doctors": 3,
    "dodgson": 1,
    "dog": 1,
    "dom": 1,
    "done": 5,
    "dorothy": 1,
    "doth": 1,
    "doubling": 1,
    "doubt": 6,
    "doubted": 3,
    "doubtful": 1,
    "doubtless": 1,
    "downstairs": 1,
    "dr": 2,
    "drage": 7,
    "draw": 1,
    "dreams": 1,
    "dropping": 1,
    "drum": 1,
    "drummer": 6,
    "drummings": 1,
    "duly": 1,
    "duny": 3,
    "dutch": 1,
    "e": 2,
    "earlier": 6,
    "early": 1,
    "ears": 1,
    "easily": 3,
    "east": 1,
    "easy": 1,
    "ed": 3,
    "edge": 1,
    "edmunds": 1,
    "edwards": 2,
    "effect": 2,
    "effort": 1,
    "eight": 1,
    "eighteenth": 1,
    "eighties": 2,
    "eighty": 1,
    "either": 1,
    "elements": 1,
    "eleven": 2,
    "elicited": 1,
    "elizabeth": 7,
    "else": 1,
    "ely": 1,
    "embodied": 1,
    "eminent": 2,
    "employment": 1,
    "end": 1,
    "endeavored": 1,
    "ends": 1,
    "enemies": 2,
    "england": 9,
    "english": 4,
    "enhanced": 1,
    "enormous": 1,
    "enough": 5,
    "ensued": 1,
    "entertained": 1,
    "entirely": 1,
    "episode": 1,
    "epoch": 2,
    "equity": 1,
    "escaped": 3,
    "especially": 3,
    "essex": 1,
    "establish": 1,
    "estate": 2,
    "estimate": 1,
    "even": 11,
    "event": 1,
    "events": 3,
    "ever": 6,
    "every": 5,
    "evidence": 27,
    "evil": 3,
    "evoked": 1,
    "exact": 2,
    "exactly": 1,
    "exalts": 1,
    "examination": 1,
    "examinations": 2,
    "examine": 1,
    "examining": 2,
    "examples": 1,
    "exceedingly": 1,
    "exception": 1,
    "exceptional": 2,
    "exceptions": 1,
    "excess": 1,
    "exchequer": 2,
    "excited": 1,
    "excitement": 1,
    "excused": 1,
    "execution": 1,
    "executions": 2,
    "exeter": 5,
    "exhibit": 1,
    "existence": 1,
    "exorcism": 1,
    "expected": 2,
    "expecting": 1,
    "expelled": 1,
    "expended": 1,
    "experiment": 1,
    "experimenter": 1,
    "experiments": 1,
    "expert": 1,
    "explained": 1,
    "explanation": 3,
    "explosion": 1,
    "exposed": 1,
    "expressed": 2,
    "extraordinarily": 1,
    "extreme": 1,
    "extremely": 1,
    "eyes": 2,
    "face": 1,
    "fact": 8,
    "failed": 2,
    "failure": 1,
    "fairer": 2,
    "fairly": 1,
    "faith": 1,
    "fall": 1,
    "fallen": 2,
    "false": 1,
    "familiar": 2,
    "family": 4,
    "famous": 2,
    "far": 5,
    "farmer": 1,
    "farreaching": 1,
    "farther": 1,
    "fashion": 1,
    "fast": 1,
    "fasted": 1,
    "fasting": 1,
    "fastings": 1,
    "father": 1,
    "favor": 3,
    "fear": 1,
    "feared": 1,
    "fearful": 1,
    "feasts": 1,
    "features": 2,
    "fee": 2,
    "feeling": 1,
    "fell": 3,
    "felon": 1,
    "felonies": 1,
    "felt": 2,
    "female": 3,
    "females": 1,
    "fenwick": 1,
    "ferreted": 1,
    "fetched": 4,
    "fighting": 1,
    "figures": 4,
    "final": 1,
    "finally": 2,
    "find": 1,
    "finding": 1,
    "finds": 1,
    "fire": 3,
    "fired": 1,
    "first": 5,
    "fit": 1,
    "fits": 8,
    "five": 4,
    "fix": 1,
    "fleet": 1,
    "flew": 1,
    "flickering": 1,
    "flies": 3,
    "flourished": 1,
    "floyd": 1,
    "fluctuation": 1,
    "fly": 1,
    "foam": 1,
    "followed": 4,
    "following": 2,
    "foot": 2,
    "forced": 1,
    "forcibly": 1,
    "forehead": 1,
    "forged": 1,
    "forgotten": 1,
    "form": 6,
    "formed": 1,
    "forms": 4,
    "forty": 2,
    "foster": 3,
    "fought": 1,
    "foul": 1,
    "found": 11,
    "four": 3,
    "fourth": 2,
    "frame": 1,
    "francis": 2,
    "frantic": 1,
    "fraud": 3,
    "free": 3,
    "freely": 1,
    "frequency": 1,
    "fretful": 1,
    "friendly": 2,
    "friends": 3,
    "full": 5,
    "fun": 1,
    "gaddesden": 1,
    "gained": 4,
    "gallows": 2,
    "game": 1,
    "gaol": 4,
    "gathered": 1,
    "gatherings": 1,
    "gave": 4,
    "general": 2,
    "generalization": 1,
    "generation": 1,
    "gentlemans": 3,
    "gentlemen": 2,
    "gentry": 1,
    "genuine": 1,
    "get": 2,
    "getting": 1,
    "gibbet": 1,
    "girl": 7,
    "girls": 5,
    "give": 1,
    "given": 5,
    "glad": 2,
    "glanvill": 6,
    "glanvills": 4,
    "glided": 1,
    "go": 6,
    "going": 3,
    "gone": 2,
    "good": 4,
    "goods": 1,
    "goodwife": 2,
    "got": 1,
    "grade": 1,
    "gradually": 1,
    "great": 7,
    "greater": 1,
    "greatest": 1,
    "greatly": 1,
    "greatshe": 1,
    "green": 1,
    "ground": 1,
    "groups": 1,
    "growing": 1,
    "guess": 3,
    "guilford": 1,
    "guilfords": 1,
    "guilt": 1,
    "guilty": 5,
    "gun": 1,
    "h": 1,
    "hale": 13,
    "hales": 2,
    "half": 1,
    "halfcentury": 1,
    "halfwitted": 1,
    "hall": 3,
    "halls": 1,
    "hand": 5,
    "handled": 1,
    "hands": 3,
    "hangd": 2,
    "hanged": 4,
    "hangings": 1,
    "hannah": 3,
    "happend": 1,
    "happened": 6,
    "happening": 1,
    "happily": 1,
    "happy": 1,
    "hard": 2,
    "hardly": 5,
    "hare": 1,
    "harm": 1,
    "harwood": 3,
    "hatred": 1,
    "hatreds": 1,
    "hauntedhouse": 1,
    "head": 2,
    "healer": 1,
    "hear": 1,
    "heard": 5,
    "heavy": 1,
    "heightened": 1,
    "held": 4,
    "hell": 1,
    "hellish": 1,
    "help": 2,
    "helped": 1,
    "henry": 2,
    "herd": 1,
    "hertfordshire": 1,
    "heywood": 3,
    "heywoods": 1,
    "hideous": 1,
    "high": 1,
    "highly": 1,
    "hindered": 1,
    "hist": 1,
    "historical": 1,
    "history": 4,
    "hit": 1,
    "hold": 1,
    "holt": 1,
    "home": 1,
    "homegrown": 1,
    "hon": 1,
    "honest": 1,
    "hopkins": 4,
    "horrible": 1,
    "horse": 1,
    "horseplay": 1,
    "hospital": 1,
    "hour": 1,
    "hours": 1,
    "house": 6,
    "however": 4,
    "humor": 1,
    "hundred": 1,
    "hung": 1,
    "hunt": 2,
    "hunter": 1,
    "hunters": 1,
    "huntsman": 1,
    "hysterical": 1,
    "ibid": 2,
    "identified": 1,
    "ignore": 1,
    "ii": 13,
    "iii": 1,
    "ill": 6,
    "illnesses": 1,
    "illustration": 1,
    "impartial": 1,
    "impersonal": 1,
    "implicated": 1,
    "implicating": 1,
    "importance": 3,
    "importuned": 1,
    "imposed": 1,
    "impossible": 1,
    "impostor": 1,
    "imposture": 2,
    "impressions": 1,
    "incendiary": 1,
    "inchanters": 1,
    "incident": 1,
    "including": 1,
    "increase": 1,
    "increased": 3,
    "increasingly": 2,
    "incredulity": 1,
    "incurred": 1,
    "indeed": 10,
    "inderwick": 2,
    "inderwicks": 2,
    "indication": 1,
    "indicted": 1,
    "indictments": 1,
    "individual": 1,
    "individuals": 2,
    "induced": 2,
    "influenced": 1,
    "informant": 1,
    "informations": 1,
    "injured": 1,
    "injuries": 1,
    "inside": 1,
    "inspired": 2,
    "instance": 6,
    "instances": 3,
    "instruments": 1,
    "intelligent": 1,
    "intent": 1,
    "interest": 7,
    "interested": 1,
    "interesting": 1,
    "interpretation": 1,
    "interregnum": 1,
    "interrupted": 1,
    "intervening": 1,
    "intimated": 1,
    "introduced": 1,
    "inveigled": 1,
    "investigated": 1,
    "investigation": 1,
    "investigators": 1,
    "invited": 1,
    "invoked": 1,
    "involuntary": 1,
    "involved": 1,
    "isle": 1,
    "itinerant": 1,
    "iv": 1,
    "j": 1,
    "james": 9,
    "jane": 1,
    "jerkin": 1,
    "joan": 3,
    "john": 9,
    "joseph": 3,
    "jottings": 1,
    "judge": 13,
    "judged": 1,
    "judges": 7,
    "judgments": 1,
    "judicial": 1,
    "judith": 1,
    "julian": 5,
    "juries": 3,
    "jury": 12,
    "justice": 30,
    "justices": 6,
    "justiceship": 1,
    "keep": 1,
    "kelyng": 4,
    "kent": 1,
    "kept": 2,
    "kill": 2,
    "killed": 1,
    "king": 3,
    "kings": 2,
    "knew": 2,
    "knight": 1,
    "knocked": 1,
    "knot": 1,
    "know": 8,
    "knowing": 1,
    "knowledge": 1,
    "known": 3,
    "laid": 1,
    "lancashire": 1,
    "lancaster": 1,
    "languages": 1,
    "large": 6,
    "largely": 2,
    "larger": 1,
    "last": 3,
    "later": 11,
    "laterthat": 1,
    "latter": 1,
    "latters": 1,
    "laughed": 1,
    "law": 9,
    "laws": 1,
    "lawyer": 1,
    "lead": 1,
    "leading": 2,
    "leaning": 1,
    "leap": 1,
    "leaped": 1,
    "learned": 1,
    "least": 2,
    "leave": 2,
    "led": 2,
    "left": 5,
    "legal": 2,
    "leggs": 1,
    "legs": 2,
    "length": 4,
    "lenient": 1,
    "less": 8,
    "let": 2,
    "letter": 2,
    "level": 1,
    "license": 1,
    "life": 6,
    "light": 2,
    "like": 3,
    "likely": 1,
    "list": 2,
    "listened": 1,
    "literary": 1,
    "literature": 3,
    "little": 9,
    "lived": 1,
    "lives": 2,
    "lloyd": 2,
    "london": 20,
    "long": 5,
    "longwitton": 1,
    "looked": 3,
    "lookout": 1,
    "lord": 4,
    "lords": 6,
    "lordship": 1,
    "lost": 1,
    "lowestoft": 2,
    "lyingin": 1,
    "mackenzie": 1,
    "made": 18,
    "magazine": 2,
    "magic": 1,
    "magical": 1,
    "magistrate": 1,
    "maid": 1,
    "maidstone": 1,
    "main": 1,
    "maintainance": 1,
    "maintained": 1,
    "make": 4,
    "makes": 1,
    "making": 2,
    "male": 1,
    "malice": 3,
    "malmesbury": 3,
    "man": 11,
    "manifestations": 1,
    "manifested": 1,
    "mans": 1,
    "many": 8,
    "margaret": 1,
    "mark": 1,
    "marked": 3,
    "marks": 1,
    "mary": 6,
    "mass": 1,
    "material": 3,
    "matrons": 2,
    "matter": 5,
    "matters": 1,
    "matthew": 7,
    "may": 6,
    "mean": 2,
    "means": 6,
    "meant": 1,
    "mecca": 1,
    "medical": 2,
    "medici": 1,
    "medicine": 2,
    "meditation": 1,
    "meet": 1,
    "meeting": 1,
    "melancholy": 2,
    "melting": 1,
    "member": 3,
    "memoirs": 1,
    "memory": 1,
    "men": 3,
    "mention": 2,
    "mentioned": 2,
    "mercies": 1,
    "mere": 4,
    "merely": 1,
    "merits": 1,
    "merrily": 1,
    "met": 2,
    "method": 3,
    "middle": 1,
    "middlesex": 2,
    "midland": 1,
    "midwife": 2,
    "might": 7,
    "mightily": 1,
    "milburne": 1,
    "mildly": 1,
    "miles": 1,
    "mind": 1,
    "minded": 1,
    "minions": 1,
    "ministers": 1,
    "minor": 1,
    "minute": 1,
    "misfortune": 1,
    "mishap": 1,
    "missed": 1,
    "mistake": 1,
    "mistress": 1,
    "misused": 1,
    "mittimus": 1,
    "modern": 2,
    "moment": 1,
    "mompesson": 7,
    "mompessons": 3,
    "money": 1,
    "monotonous": 1,
    "month": 1,
    "mother": 4,
    "moulded": 1,
    "mouth": 3,
    "mr": 7,
    "mrs": 3,
    "mss": 1,
    "much": 10,
    "multiply": 1,
    "must": 6,
    "mutter": 1,
    "nail": 2,
    "nails": 3,
    "name": 10,
    "named": 2,
    "narrative": 1,
    "nathan": 1,
    "nations": 1,
    "natural": 1,
    "nature": 1,
    "nauseam": 1,
    "nauseating": 1,
    "near": 2,
    "nearly": 2,
    "necessary": 2,
    "need": 1,
    "needles": 2,
    "needs": 1,
    "negative": 1,
    "neighbors": 3,
    "neither": 1,
    "never": 4,
    "nevertheless": 5,
    "new": 3,
    "newcastle": 4,
    "news": 1,
    "next": 3,
    "nice": 1,
    "nicholas": 1,
    "night": 4,
    "nineteen": 1,
    "nineties": 1,
    "noise": 1,
    "noisemaker": 1,
    "noises": 1,
    "noisy": 1,
    "nonconformists": 1,
    "none": 2,
    "nonpartisan": 1,
    "north": 13,
    "northampton": 1,
    "northamptonshire": 1,
    "northern": 1,
    "norths": 1,
    "northumberland": 2,
    "notand": 1,
    "note": 3,
    "noted": 2,
    "notes": 2,
    "noteworthy": 1,
    "nothing": 4,
    "noting": 1,
    "notions": 1,
    "novel": 1,
    "nullify": 1,
    "number": 5,
    "numbers": 1,
    "numerous": 1,
    "observed": 3,
    "obvious": 1,
    "occasion": 2,
    "occasional": 1,
    "occasioned": 1,
    "occasions": 2,
    "occurred": 3,
    "october": 1,
    "offered": 3,
    "office": 1,
    "often": 5,
    "ogle": 1,
    "oh": 2,
    "old": 8,
    "oliver": 1,
    "one": 40,
    "ones": 1,
    "onslowwriting": 1,
    "op": 7,
    "open": 1,
    "operation": 1,
    "operations": 2,
    "opinion": 8,
    "oppressing": 1,
    "order": 1,
    "orderd": 1,
    "orderly": 1,
    "orders": 2,
    "ordinary": 2,
    "others": 4,
    "outcome": 5,
    "outcry": 1,
    "outside": 2,
    "overlooked": 1,
    "overwhelmd": 1,
    "owed": 1,
    "owned": 1,
    "p": 2,
    "pacea": 1,
    "pacy": 2,
    "pain": 1,
    "pains": 1,
    "pamphlet": 1,
    "panic": 1,
    "panted": 1,
    "parents": 2,
    "parish": 2,
    "park": 1,
    "parliament": 2,
    "paroxysms": 2,
    "part": 13,
    "particular": 2,
    "particularly": 2,
    "parties": 2,
    "parts": 1,
    "party": 1,
    "passed": 2,
    "passion": 1,
    "patches": 1,
    "patient": 2,
    "patients": 2,
    "pay": 1,
    "peace": 12,
    "peacock": 4,
    "pemberton": 1,
    "penalties": 1,
    "penny": 1,
    "pensans": 1,
    "people": 7,
    "pepper": 1,
    "per": 1,
    "performance": 1,
    "perhaps": 7,
    "peril": 1,
    "period": 12,
    "perplexity": 1,
    "person": 1,
    "personal": 1,
    "persons": 3,
    "pestilent": 1,
    "petition": 1,
    "petticoat": 1,
    "phenomena": 1,
    "philosophy": 1,
    "phisitian": 1,
    "physician": 3,
    "physicians": 1,
    "physiological": 1,
    "piece": 1,
    "pieces": 2,
    "pins": 4,
    "pipe": 3,
    "pistol": 1,
    "place": 2,
    "places": 1,
    "played": 4,
    "playing": 2,
    "plot": 1,
    "point": 4,
    "pointed": 2,
    "pointing": 2,
    "points": 3,
    "political": 1,
    "poor": 9,
    "popping": 1,
    "popular": 3,
    "porch": 1,
    "position": 1,
    "possessed": 2,
    "possession": 5,
    "possessions": 1,
    "possibility": 1,
    "possible": 3,
    "pounds": 1,
    "poverty": 1,
    "powell": 1,
    "powers": 1,
    "pp": 1,
    "practice": 5,
    "practices": 1,
    "prayed": 1,
    "prayer": 3,
    "preceding": 1,
    "precision": 1,
    "preface": 2,
    "prescribed": 2,
    "presence": 1,
    "present": 4,
    "presented": 3,
    "presiding": 3,
    "pretenders": 1,
    "prey": 1,
    "principal": 1,
    "principles": 1,
    "printed": 1,
    "prison": 2,
    "prisoners": 2,
    "prisons": 1,
    "privy": 1,
    "probability": 2,
    "probably": 7,
    "problems": 1,
    "process": 1,
    "produced": 1,
    "professed": 1,
    "profound": 1,
    "proof": 4,
    "proper": 2,
    "prophecy": 1,
    "proportion": 3,
    "prosecution": 4,
    "prove": 2,
    "proved": 2,
    "provided": 1,
    "proving": 1,
    "psychic": 1,
    "pt": 7,
    "public": 5,
    "published": 2,
    "punishment": 1,
    "puritan": 2,
    "puritans": 1,
    "purpose": 1,
    "put": 3,
    "quarrelsome": 1,
    "quarter": 1,
    "queen": 1,
    "queries": 1,
    "question": 2,
    "questioned": 1,
    "questions": 1,
    "quickly": 1,
    "quiet": 2,
    "quietus": 1,
    "quite": 5,
    "quote": 1,
    "radius": 1,
    "raine": 1,
    "rainsford": 5,
    "ramess": 1,
    "ran": 2,
    "rapid": 1,
    "rare": 1,
    "rarely": 1,
    "rarity": 1,
    "rashly": 1,
    "rate": 2,
    "rather": 1,
    "rats": 1,
    "raymond": 7,
    "raymonds": 1,
    "reached": 1,
    "read": 1,
    "reader": 3,
    "ready": 2,
    "reality": 2,
    "realize": 1,
    "realized": 1,
    "realm": 1,
    "reason": 1,
    "reasoned": 1,
    "recalling": 1,
    "received": 1,
    "recent": 1,
    "reclining": 1,
    "record": 2,
    "records": 4,
    "recovered": 1,
    "red": 1,
    "redman": 1,
    "references": 1,
    "reflected": 1,
    "refuse": 1,
    "refused": 1,
    "regarded": 1,
    "regicides": 1,
    "regretted": 1,
    "regular": 2,
    "reign": 3,
    "reiterated": 1,
    "relate": 1,
    "related": 1,
    "relation": 4,
    "relations": 1,
    "released": 1,
    "releases": 1,
    "relief": 1,
    "religio": 1,
    "reluctant": 1,
    "remained": 2,
    "remark": 1,
    "remarkable": 1,
    "remarkably": 1,
    "remember": 1,
    "reminded": 1,
    "remote": 2,
    "render": 2,
    "repeat": 1,
    "repetition": 2,
    "reporter": 1,
    "reports": 1,
    "representative": 1,
    "reprieve": 1,
    "reproved": 1,
    "reputation": 6,
    "reputed": 1,
    "requisitioned": 1,
    "reresby": 2,
    "resembled": 1,
    "resented": 1,
    "respect": 1,
    "respectively": 1,
    "responsibilities": 1,
    "responsible": 1,
    "rest": 1,
    "restoration": 4,
    "restrained": 1,
    "result": 3,
    "resulted": 1,
    "results": 2,
    "retainers": 1,
    "return": 1,
    "returned": 3,
    "returning": 1,
    "reveal": 1,
    "revenge": 1,
    "reverend": 1,
    "revival": 2,
    "rich": 1,
    "richard": 2,
    "rid": 1,
    "ridden": 1,
    "ridding": 1,
    "riding": 2,
    "righting": 1,
    "rigid": 1,
    "risk": 3,
    "robert": 2,
    "roberts": 1,
    "roger": 5,
    "roofs": 1,
    "room": 2,
    "rooms": 1,
    "rose": 2,
    "roused": 1,
    "royal": 3,
    "rt": 1,
    "rule": 1,
    "ruled": 1,
    "ruling": 4,
    "rulings": 1,
    "run": 3,
    "running": 1,
    "r\u00e9gime": 1,
    "r\u00f4le": 1,
    "sadducees": 1,
    "sadducismus": 5,
    "said": 13,
    "saith": 2,
    "salem": 1,
    "salisbury": 4,
    "sat": 2,
    "satan": 1,
    "satisfaction": 1,
    "save": 2,
    "saw": 11,
    "say": 10,
    "says": 3,
    "sayso": 1,
    "scarce": 1,
    "scare": 1,
    "science": 1,
    "scorched": 1,
    "score": 1,
    "scotland": 1,
    "scott": 1,
    "scratch": 1,
    "scratched": 1,
    "scripture": 2,
    "scriptures": 1,
    "second": 2,
    "sedulously": 1,
    "see": 14,
    "seeking": 1,
    "seem": 6,
    "seems": 6,
    "seen": 8,
    "selden": 1,
    "selfconstituted": 1,
    "send": 2,
    "sending": 2,
    "sensation": 1,
    "sense": 1,
    "sensible": 1,
    "sensibly": 1,
    "sent": 5,
    "sentence": 1,
    "sentenced": 3,
    "sentiment": 3,
    "series": 1,
    "serious": 3,
    "seriously": 1,
    "serjeant": 3,
    "serjeants": 1,
    "servant": 2,
    "servants": 1,
    "served": 1,
    "set": 2,
    "seven": 4,
    "seventeenth": 4,
    "seventeenthcentury": 2,
    "seventies": 1,
    "several": 5,
    "severely": 2,
    "shall": 4,
    "shape": 1,
    "sharp": 1,
    "shattered": 1,
    "sheds": 1,
    "sheep": 1,
    "sheets": 1,
    "shilling": 2,
    "shoes": 1,
    "short": 2,
    "shortly": 1,
    "shortlywas": 1,
    "shot": 1,
    "show": 3,
    "showed": 2,
    "showing": 1,
    "shows": 1,
    "shred": 1,
    "shrewd": 1,
    "shuffle": 1,
    "sic": 2,
    "sick": 3,
    "side": 3,
    "sidelights": 1,
    "significant": 1,
    "similar": 4,
    "simple": 1,
    "simplified": 1,
    "simply": 1,
    "since": 1,
    "sing": 1,
    "single": 5,
    "singular": 1,
    "singularly": 1,
    "sir": 12,
    "sitting": 1,
    "situation": 1,
    "six": 3,
    "sixteenth": 1,
    "sixties": 1,
    "skeptical": 1,
    "skeptics": 1,
    "skill": 1,
    "skins": 1,
    "slight": 1,
    "small": 4,
    "smith": 1,
    "smoked": 1,
    "smoking": 1,
    "smoothwitted": 1,
    "soc": 2,
    "society": 1,
    "soldier": 1,
    "somerset": 4,
    "something": 1,
    "sometimes": 3,
    "somewhat": 5,
    "son": 3,
    "soon": 2,
    "sort": 9,
    "soul": 1,
    "sources": 1,
    "southern": 1,
    "southwark": 2,
    "southwestern": 1,
    "spanned": 1,
    "speaker": 1,
    "special": 1,
    "specified": 1,
    "specimen": 1,
    "spectral": 4,
    "spectres": 2,
    "speech": 1,
    "speed": 1,
    "spell": 2,
    "spent": 1,
    "spirit": 1,
    "spirits": 9,
    "spiritual": 1,
    "spit": 1,
    "spite": 5,
    "spitting": 1,
    "spoke": 2,
    "spoken": 1,
    "spot": 1,
    "st": 2,
    "stages": 1,
    "stand": 1,
    "start": 1,
    "started": 2,
    "state": 2,
    "stated": 1,
    "statement": 2,
    "statements": 2,
    "status": 1,
    "statute": 1,
    "stealing": 1,
    "stemmed": 1,
    "stern": 1,
    "stick": 1,
    "still": 5,
    "stir": 1,
    "stirred": 1,
    "stolen": 1,
    "stomacher": 1,
    "stooped": 1,
    "stories": 2,
    "storm": 1,
    "story": 12,
    "stothard": 1,
    "stout": 1,
    "strange": 6,
    "strangely": 1,
    "stranger": 2,
    "stray": 2,
    "strength": 1,
    "strengthened": 1,
    "stretched": 3,
    "striking": 1,
    "strong": 3,
    "stuarts": 3,
    "student": 2,
    "stupid": 1,
    "style": 2,
    "subdivision": 1,
    "subject": 4,
    "submitted": 2,
    "substance": 1,
    "subtilty": 1,
    "subtle": 1,
    "successful": 4,
    "suckled": 1,
    "sudden": 1,
    "suddenly": 2,
    "suffered": 3,
    "suffolk": 1,
    "suggest": 1,
    "suggestion": 2,
    "sum": 2,
    "summer": 1,
    "sunday": 1,
    "supernatural": 2,
    "superstition": 5,
    "supporters": 1,
    "suppose": 2,
    "supposed": 2,
    "suppositions": 1,
    "sure": 2,
    "surry": 1,
    "surtees": 1,
    "susanna": 2,
    "suspect": 1,
    "suspected": 4,
    "suspecting": 1,
    "suspicion": 3,
    "suspicious": 2,
    "sussex": 2,
    "swooning": 1,
    "swords": 1,
    "sworn": 2,
    "swounding": 1,
    "sympathizing": 1,
    "take": 3,
    "taken": 11,
    "taking": 4,
    "tale": 1,
    "talent": 1,
    "tales": 2,
    "talked": 1,
    "tallied": 2,
    "taunton": 1,
    "tauntondean": 1,
    "tedworth": 4,
    "tell": 1,
    "telling": 1,
    "tells": 1,
    "temperance": 2,
    "temptation": 3,
    "ten": 1,
    "tendencies": 1,
    "tendency": 1,
    "tender": 1,
    "tenyearold": 1,
    "term": 2,
    "terribly": 1,
    "terrified": 1,
    "test": 1,
    "testified": 3,
    "testify": 1,
    "testimony": 6,
    "tests": 1,
    "texts": 1,
    "thank": 1,
    "thankful": 1,
    "thence": 1,
    "theological": 1,
    "theologically": 1,
    "theology": 1,
    "theory": 2,
    "therefore": 1,
    "thing": 1,
    "things": 2,
    "thinking": 1,
    "third": 3,
    "thirty": 1,
    "thomas": 3,
    "thoroughly": 1,
    "though": 3,
    "thought": 4,
    "thoughtlessly": 1,
    "threatening": 1,
    "threats": 1,
    "three": 10,
    "thrilling": 1,
    "throne": 1,
    "throughout": 2,
    "thrown": 6,
    "till": 1,
    "tilling": 4,
    "time": 24,
    "times": 3,
    "tissue": 1,
    "toad": 8,
    "tobacco": 1,
    "together": 4,
    "told": 11,
    "tonken": 1,
    "took": 6,
    "torturing": 1,
    "total": 1,
    "touched": 3,
    "towards": 1,
    "town": 5,
    "traded": 1,
    "tradesman": 1,
    "tragedy": 1,
    "tragic": 1,
    "transaction": 1,
    "transcendent": 1,
    "transported": 1,
    "travels": 1,
    "treatise": 1,
    "treatment": 2,
    "trembles": 1,
    "trial": 18,
    "trials": 13,
    "trickery": 1,
    "tricks": 1,
    "tried": 8,
    "trifling": 1,
    "triumphatus": 5,
    "trouble": 1,
    "troubled": 2,
    "troubles": 2,
    "true": 8,
    "trustworthiness": 1,
    "trustworthy": 1,
    "truth": 1,
    "try": 1,
    "tryal": 3,
    "trying": 1,
    "tune": 1,
    "turned": 3,
    "turner": 1,
    "turning": 1,
    "twelve": 1,
    "twenty": 4,
    "twentyeight": 1,
    "twentyfour": 1,
    "twentyseven": 1,
    "twilight": 1,
    "two": 18,
    "twopenny": 1,
    "type": 1,
    "typical": 3,
    "unable": 1,
    "unbewitch": 1,
    "uncovered": 2,
    "understand": 2,
    "understanding": 1,
    "understood": 1,
    "unfortunately": 1,
    "unhappily": 2,
    "unique": 1,
    "unknown": 2,
    "unlearned": 1,
    "unnatural": 1,
    "unnecessary": 1,
    "unpleasant": 1,
    "unreasonable": 1,
    "unsubstantial": 1,
    "untrustworthy": 1,
    "unusual": 1,
    "upheld": 1,
    "upholders": 1,
    "upon": 26,
    "upside": 1,
    "urge": 1,
    "urged": 1,
    "us": 7,
    "use": 4,
    "used": 1,
    "using": 1,
    "usual": 5,
    "usually": 3,
    "uttered": 1,
    "vague": 1,
    "valuables": 1,
    "vanishd": 1,
    "variety": 1,
    "various": 1,
    "verdict": 5,
    "verdicts": 1,
    "verily": 1,
    "vicinity": 1,
    "view": 1,
    "village": 1,
    "villanies": 1,
    "visitors": 2,
    "voluble": 2,
    "voluntary": 1,
    "vomiting": 1,
    "waged": 1,
    "waking": 1,
    "war": 3,
    "warm": 1,
    "wars": 3,
    "warwick": 1,
    "watched": 2,
    "way": 5,
    "ways": 2,
    "weakness": 2,
    "weary": 1,
    "webb": 1,
    "webster": 1,
    "week": 1,
    "weeks": 1,
    "weight": 1,
    "weird": 1,
    "well": 8,
    "went": 8,
    "west": 1,
    "western": 3,
    "whence": 1,
    "whenever": 1,
    "whether": 3,
    "whole": 2,
    "whose": 5,
    "wicked": 1,
    "wide": 2,
    "widely": 1,
    "wider": 1,
    "wife": 1,
    "wild": 1,
    "wilkin": 1,
    "william": 1,
    "wiltshire": 3,
    "win": 1,
    "winchester": 1,
    "window": 2,
    "wise": 2,
    "wish": 1,
    "wished": 1,
    "wishes": 1,
    "witch": 39,
    "witchcraft": 25,
    "witchcrafts": 1,
    "witchell": 2,
    "witches": 23,
    "witchfinder": 2,
    "witchtriers": 1,
    "within": 3,
    "without": 2,
    "withstand": 1,
    "witness": 8,
    "witnessed": 1,
    "witnesses": 4,
    "woman": 22,
    "womans": 1,
    "women": 17,
    "womenwas": 1,
    "wonderful": 2,
    "wonders": 1,
    "woodhouse": 1,
    "woodhouses": 1,
    "woodstock": 2,
    "word": 1,
    "words": 3,
    "work": 3,
    "works": 2,
    "world": 2,
    "worried": 1,
    "worst": 1,
    "worth": 4,
    "worthington": 1,
    "would": 27,
    "wouldbe": 1,
    "wretched": 1,
    "wringing": 1,
    "writer": 1,
    "writers": 1,
    "written": 1,
    "wrote": 2,
    "xi": 1,
    "xiv": 1,
    "xviii": 1,
    "xxx": 1,
    "yarmouth": 1,
    "year": 4,
    "years": 19,
    "yellow": 1,
    "yet": 3,
    "yielded": 2,
    "york": 8,
    "yorkshire": 5,
    "young": 2,
    "youth": 1,
    "yowell": 1,
    "zeal": 1,
    "zealous": 2
}
