{
    "abandoned": 1,
    "abandoning": 1,
    "abandonment": 1,
    "abhorrent": 1,
    "ability": 1,
    "able": 1,
    "abode": 2,
    "abound": 1,
    "abroad": 1,
    "abrogated": 1,
    "abstaining": 1,
    "abuse": 1,
    "abusing": 1,
    "accept": 1,
    "accessary": 1,
    "accession": 1,
    "accomplish": 1,
    "accomplishments": 1,
    "according": 5,
    "accordingly": 2,
    "account": 4,
    "accounted": 3,
    "accounting": 1,
    "accounts": 1,
    "accurate": 2,
    "accusation": 1,
    "accused": 2,
    "acknowledged": 1,
    "acknowledges": 1,
    "acknowledgment": 1,
    "acquainted": 3,
    "acquire": 2,
    "act": 3,
    "actions": 1,
    "acts": 2,
    "actual": 3,
    "actually": 3,
    "adam": 2,
    "added": 2,
    "additional": 1,
    "addressed": 2,
    "addresses": 1,
    "adhered": 1,
    "adherence": 1,
    "administration": 1,
    "admired": 1,
    "admitted": 4,
    "admitting": 1,
    "adopt": 1,
    "adopted": 5,
    "adoration": 3,
    "adore": 1,
    "advanced": 2,
    "advantage": 3,
    "advent": 2,
    "advise": 1,
    "affected": 1,
    "affirm": 1,
    "affirmed": 1,
    "afflictions": 1,
    "afforded": 2,
    "affording": 1,
    "affrights": 1,
    "afraid": 1,
    "afterwards": 1,
    "age": 1,
    "agencies": 1,
    "agency": 4,
    "agents": 2,
    "ages": 5,
    "agesthus": 1,
    "agreeably": 1,
    "agreed": 2,
    "ahab": 1,
    "aid": 3,
    "airth": 1,
    "alarmed": 1,
    "alienation": 1,
    "alike": 2,
    "allay": 1,
    "alleged": 1,
    "allegiance": 1,
    "alliances": 1,
    "allowed": 2,
    "alluded": 5,
    "almanacks": 1,
    "almighty": 8,
    "almightys": 1,
    "almost": 3,
    "alone": 1,
    "already": 2,
    "also": 10,
    "altars": 1,
    "alter": 1,
    "although": 8,
    "america": 4,
    "american": 1,
    "americaopinion": 1,
    "amid": 1,
    "among": 17,
    "amongst": 2,
    "amused": 1,
    "analogous": 1,
    "ancestors": 3,
    "ancient": 3,
    "ancients": 1,
    "angel": 4,
    "angels": 6,
    "angelswere": 1,
    "animals": 1,
    "annihilating": 1,
    "announced": 1,
    "announcement": 1,
    "annoyance": 1,
    "another": 7,
    "answer": 5,
    "antediluvian": 1,
    "anticipating": 1,
    "antiquitythe": 1,
    "anubis": 1,
    "anxious": 1,
    "anyone": 1,
    "anything": 3,
    "ape": 1,
    "aped": 1,
    "apollo": 2,
    "apolloa": 1,
    "apology": 1,
    "apostasy": 1,
    "apostate": 2,
    "apostle": 1,
    "apostles": 4,
    "appalling": 1,
    "apparition": 5,
    "appear": 2,
    "appearance": 10,
    "appeared": 2,
    "appears": 4,
    "applied": 3,
    "apply": 1,
    "apprehended": 3,
    "approached": 1,
    "approbation": 1,
    "approved": 1,
    "apt": 1,
    "arabian": 1,
    "arched": 1,
    "archfiend": 1,
    "argued": 1,
    "argument": 2,
    "arise": 1,
    "arisen": 1,
    "arising": 2,
    "armed": 2,
    "armies": 1,
    "arms": 1,
    "army": 2,
    "arose": 1,
    "around": 3,
    "arrive": 1,
    "arrived": 1,
    "art": 2,
    "artdifficulties": 1,
    "article": 2,
    "articles": 1,
    "artisans": 1,
    "arts": 3,
    "ascertain": 1,
    "ascertained": 1,
    "ascribe": 1,
    "ascribed": 4,
    "ashtaroth": 1,
    "asking": 1,
    "asks": 1,
    "ass": 1,
    "assent": 1,
    "assert": 1,
    "asserted": 1,
    "assigning": 1,
    "assistance": 7,
    "assistant": 1,
    "assisting": 1,
    "associations": 1,
    "assume": 1,
    "assumed": 4,
    "assured": 3,
    "assyrian": 1,
    "astrological": 1,
    "attaining": 1,
    "attainments": 1,
    "attempt": 2,
    "attempted": 1,
    "attend": 1,
    "attended": 1,
    "attending": 2,
    "attested": 2,
    "attribute": 1,
    "attributes": 2,
    "audacious": 1,
    "augmented": 1,
    "auguries": 1,
    "augury": 1,
    "auspices": 1,
    "author": 2,
    "authorities": 2,
    "authority": 1,
    "authorizing": 1,
    "avenging": 1,
    "avoid": 1,
    "avoided": 1,
    "awaiting": 1,
    "away": 2,
    "awful": 4,
    "awkward": 1,
    "azrael": 1,
    "baal": 2,
    "baalim": 1,
    "bacchus": 1,
    "backsliders": 1,
    "balaam": 1,
    "balak": 1,
    "baleful": 1,
    "banishment": 1,
    "banner": 1,
    "barbarians": 1,
    "barbarism": 1,
    "barbarous": 1,
    "bat": 1,
    "bathed": 1,
    "battle": 1,
    "bear": 2,
    "bearing": 1,
    "beastly": 1,
    "beat": 1,
    "beatitude": 1,
    "beautiful": 1,
    "became": 4,
    "become": 2,
    "becoming": 1,
    "began": 2,
    "behalf": 1,
    "behind": 1,
    "beings": 5,
    "belief": 7,
    "believe": 5,
    "believed": 3,
    "believer": 1,
    "believing": 2,
    "ben": 1,
    "beneath": 1,
    "benefit": 1,
    "benevolent": 1,
    "benighted": 1,
    "benign": 1,
    "besides": 1,
    "best": 1,
    "better": 2,
    "betwixt": 1,
    "beyond": 2,
    "bible": 2,
    "bibles": 1,
    "biographia": 1,
    "birds": 1,
    "birth": 1,
    "blame": 1,
    "blasphemous": 1,
    "blessed": 3,
    "blessings": 1,
    "blighting": 1,
    "block": 1,
    "bloodshed": 1,
    "blue": 1,
    "bodily": 2,
    "boldly": 2,
    "bond": 1,
    "book": 4,
    "books": 1,
    "borgia": 1,
    "borgian": 1,
    "borrowed": 2,
    "bottom": 1,
    "bound": 1,
    "branch": 1,
    "breasts": 1,
    "breathed": 2,
    "bridegrooms": 1,
    "bridled": 1,
    "brief": 1,
    "brilliant": 1,
    "bring": 2,
    "british": 1,
    "broiling": 1,
    "brokenspirited": 1,
    "bronze": 1,
    "brought": 4,
    "brutal": 1,
    "brute": 1,
    "brutish": 2,
    "burned": 2,
    "burning": 1,
    "byroad": 1,
    "c": 2,
    "caftans": 1,
    "calamities": 1,
    "calculated": 2,
    "call": 5,
    "called": 12,
    "came": 3,
    "cameronian": 1,
    "cameronians": 1,
    "cannot": 3,
    "canonized": 1,
    "capable": 3,
    "capacity": 2,
    "capital": 6,
    "capitally": 2,
    "captivity": 1,
    "cardinal": 1,
    "carried": 2,
    "carrying": 1,
    "carved": 1,
    "case": 7,
    "cases": 4,
    "catholic": 1,
    "catholics": 1,
    "catholicsresult": 1,
    "cattle": 1,
    "cause": 2,
    "caused": 2,
    "ceased": 1,
    "celebrated": 1,
    "celestial": 2,
    "cell": 1,
    "censure": 1,
    "century": 3,
    "ceremonies": 1,
    "certain": 10,
    "certainly": 2,
    "certainty": 4,
    "challenging": 1,
    "chamber": 1,
    "chance": 1,
    "change": 1,
    "changed": 1,
    "chap": 1,
    "chapels": 1,
    "chapter": 3,
    "chapters": 1,
    "character": 9,
    "characteristic": 1,
    "charge": 3,
    "charmer": 1,
    "charmers": 1,
    "charms": 6,
    "chart": 2,
    "chasaph": 2,
    "chastised": 1,
    "chastisement": 1,
    "cheated": 1,
    "chiefly": 1,
    "chiefs": 1,
    "children": 4,
    "chill": 1,
    "chivalrous": 1,
    "chose": 1,
    "chosen": 4,
    "christendom": 1,
    "christian": 13,
    "christians": 8,
    "chronicle": 1,
    "chronicles": 1,
    "church": 7,
    "churches": 1,
    "churchmen": 1,
    "circulated": 1,
    "circumstances": 1,
    "city": 1,
    "class": 7,
    "classed": 1,
    "classic": 3,
    "classical": 2,
    "classing": 1,
    "clear": 3,
    "clement": 1,
    "clerk": 1,
    "clients": 1,
    "clothed": 1,
    "cloven": 2,
    "clumsy": 1,
    "code": 1,
    "coeur": 2,
    "collected": 1,
    "colonists": 4,
    "colony": 1,
    "colt": 3,
    "combat": 2,
    "combined": 3,
    "come": 1,
    "comes": 1,
    "coming": 1,
    "command": 2,
    "commands": 3,
    "commission": 1,
    "committed": 2,
    "common": 6,
    "commonly": 1,
    "commonwealth": 1,
    "communicate": 1,
    "communicated": 2,
    "communication": 6,
    "communications": 1,
    "compact": 2,
    "companions": 1,
    "company": 1,
    "comparatively": 1,
    "compared": 1,
    "compel": 1,
    "compelled": 3,
    "competition": 1,
    "complain": 1,
    "complaint": 2,
    "comprehended": 1,
    "comprehends": 2,
    "comrade": 1,
    "conceal": 1,
    "concealed": 1,
    "conceded": 1,
    "conceive": 2,
    "conceived": 1,
    "conceiving": 1,
    "concerned": 2,
    "concerning": 1,
    "conclude": 2,
    "concluding": 1,
    "conclusively": 1,
    "concur": 1,
    "condition": 2,
    "conducing": 1,
    "conducted": 1,
    "conferred": 1,
    "confident": 1,
    "confined": 1,
    "confirm": 1,
    "confirmation": 1,
    "confound": 2,
    "confuted": 1,
    "conjuration": 1,
    "conjured": 2,
    "conjurer": 1,
    "conjurers": 2,
    "connected": 3,
    "connexion": 4,
    "conquer": 1,
    "conquered": 1,
    "conquest": 1,
    "consciousness": 1,
    "consecrated": 1,
    "consequence": 3,
    "consequences": 3,
    "consequently": 1,
    "considered": 2,
    "considering": 1,
    "consist": 2,
    "constantine": 1,
    "constantly": 1,
    "constitute": 1,
    "constructed": 1,
    "consulted": 3,
    "consulter": 1,
    "contains": 1,
    "contend": 1,
    "contended": 1,
    "continent": 1,
    "continual": 1,
    "continue": 3,
    "continued": 2,
    "contract": 2,
    "contrary": 2,
    "contributed": 2,
    "contributions": 1,
    "controversy": 1,
    "converse": 2,
    "conversion": 1,
    "converts": 1,
    "convey": 1,
    "conveyed": 1,
    "conviction": 2,
    "convinced": 1,
    "cor": 1,
    "correct": 1,
    "correction": 1,
    "corresponding": 2,
    "corresponds": 1,
    "corroboration": 1,
    "corrupted": 1,
    "cotton": 2,
    "couch": 1,
    "could": 19,
    "counsel": 2,
    "countenance": 2,
    "countries": 1,
    "country": 2,
    "county": 1,
    "courland": 1,
    "course": 7,
    "craft": 1,
    "crammed": 1,
    "created": 1,
    "creation": 3,
    "creator": 1,
    "credible": 1,
    "credit": 3,
    "credited": 1,
    "credulous": 1,
    "creeds": 1,
    "crime": 17,
    "crimes": 1,
    "criminal": 4,
    "criminals": 1,
    "crops": 1,
    "cruelties": 1,
    "cruelty": 2,
    "crusaders": 1,
    "cunning": 1,
    "cur": 1,
    "cures": 1,
    "curing": 1,
    "curses": 1,
    "cursorily": 1,
    "cursory": 1,
    "cut": 2,
    "cuts": 1,
    "cutting": 1,
    "cymbals": 1,
    "dairies": 1,
    "dale": 1,
    "dam": 2,
    "dance": 1,
    "dare": 1,
    "dared": 1,
    "dark": 3,
    "darker": 1,
    "darkest": 1,
    "darkness": 1,
    "dashed": 1,
    "date": 1,
    "daughter": 1,
    "daughters": 2,
    "day": 1,
    "days": 6,
    "de": 2,
    "deadly": 1,
    "dealt": 3,
    "death": 12,
    "deatha": 1,
    "debarring": 1,
    "deceit": 1,
    "deceitful": 1,
    "deceived": 2,
    "deceiving": 2,
    "deception": 2,
    "deceptions": 1,
    "decide": 1,
    "deciding": 1,
    "declaration": 1,
    "declare": 1,
    "declared": 3,
    "dedicated": 1,
    "deduced": 1,
    "deemed": 1,
    "deep": 2,
    "deepest": 1,
    "deeply": 1,
    "defeat": 4,
    "defection": 1,
    "defence": 1,
    "defend": 1,
    "defiance": 1,
    "degraded": 1,
    "degree": 9,
    "deities": 8,
    "deity": 14,
    "deliver": 1,
    "delivered": 1,
    "delivering": 1,
    "delphos": 1,
    "deluded": 3,
    "deluding": 1,
    "delusion": 2,
    "delusions": 1,
    "demanded": 1,
    "demon": 4,
    "demoniac": 1,
    "demoniacal": 4,
    "demoniacsthe": 1,
    "demonology": 7,
    "demons": 11,
    "demonsmore": 1,
    "demonstration": 1,
    "denoting": 1,
    "denounced": 4,
    "denunciations": 1,
    "deny": 4,
    "denying": 1,
    "departed": 1,
    "departure": 1,
    "derangement": 1,
    "derived": 4,
    "descend": 1,
    "descent": 1,
    "described": 3,
    "describes": 1,
    "description": 4,
    "desertions": 1,
    "deserve": 1,
    "deservedly": 2,
    "deserving": 1,
    "designed": 2,
    "desire": 1,
    "desired": 6,
    "desires": 1,
    "despair": 2,
    "despairing": 1,
    "desperation": 1,
    "despised": 1,
    "destined": 1,
    "destiny": 1,
    "destroy": 1,
    "detailed": 1,
    "detected": 1,
    "determine": 1,
    "deuteronomy": 1,
    "devices": 2,
    "devil": 8,
    "devils": 6,
    "devoid": 1,
    "devoted": 1,
    "devout": 2,
    "diabolic": 1,
    "diabolical": 2,
    "dictated": 1,
    "died": 2,
    "diet": 1,
    "different": 10,
    "differently": 1,
    "difficult": 2,
    "difficulties": 1,
    "diffuse": 1,
    "dignified": 1,
    "dignity": 1,
    "digress": 1,
    "dim": 1,
    "direct": 6,
    "directed": 2,
    "directly": 3,
    "disasters": 1,
    "disciples": 1,
    "discipline": 2,
    "discontents": 1,
    "discouraged": 1,
    "discover": 2,
    "discovered": 2,
    "discoverers": 1,
    "discussion": 2,
    "disease": 1,
    "diseases": 2,
    "disgustingly": 1,
    "disheartened": 1,
    "dismal": 1,
    "dismounted": 1,
    "disobedience": 2,
    "disorder": 1,
    "disowning": 1,
    "dispatched": 1,
    "dispatching": 1,
    "dispel": 1,
    "dispensation": 5,
    "dispensationa": 1,
    "dispensationit": 1,
    "dispersing": 1,
    "dispersion": 1,
    "display": 1,
    "displayed": 3,
    "displays": 3,
    "displeasing": 1,
    "displeasure": 1,
    "disposed": 2,
    "disquieted": 3,
    "dissenters": 2,
    "dissentersconclusion": 1,
    "distance": 2,
    "distinguished": 1,
    "districts": 1,
    "disturb": 2,
    "disturbed": 1,
    "diverted": 1,
    "divination": 1,
    "divine": 13,
    "divineress": 1,
    "divining": 4,
    "divinity": 4,
    "divisions": 1,
    "doctor": 1,
    "doctrine": 2,
    "doctrines": 1,
    "dog": 1,
    "domestic": 1,
    "doom": 1,
    "door": 1,
    "double": 1,
    "doubt": 3,
    "doubtful": 3,
    "dr": 1,
    "dragon": 2,
    "drawnwe": 1,
    "dread": 1,
    "dreadful": 1,
    "dream": 2,
    "dreams": 1,
    "drear": 1,
    "dressed": 1,
    "drive": 1,
    "driven": 1,
    "drooping": 1,
    "dropped": 1,
    "drove": 1,
    "drugs": 1,
    "duke": 1,
    "dumb": 1,
    "dwelt": 1,
    "dying": 1,
    "earlier": 1,
    "earliest": 1,
    "early": 2,
    "ears": 2,
    "earth": 6,
    "earthly": 1,
    "earththat": 1,
    "easily": 1,
    "east": 2,
    "easy": 1,
    "eating": 1,
    "ecclesiasticus": 1,
    "edged": 1,
    "edifying": 1,
    "educated": 1,
    "effect": 2,
    "effected": 1,
    "effectually": 1,
    "egypt": 2,
    "egyptian": 1,
    "either": 10,
    "ejected": 2,
    "eke": 1,
    "elder": 1,
    "elect": 1,
    "elude": 1,
    "elymas": 1,
    "emancipation": 1,
    "embarrassed": 1,
    "embassy": 1,
    "embodied": 1,
    "embraced": 1,
    "emphatic": 1,
    "employ": 1,
    "employed": 1,
    "enabled": 2,
    "enactments": 1,
    "enchanted": 1,
    "enchanter": 1,
    "enchantments": 2,
    "encounter": 2,
    "encountered": 1,
    "encouraged": 1,
    "encouragement": 1,
    "end": 4,
    "endeavour": 3,
    "endeavoured": 1,
    "endor": 5,
    "endoraccount": 1,
    "endowed": 1,
    "enemies": 5,
    "enemy": 4,
    "england": 2,
    "english": 4,
    "englishman": 1,
    "engraved": 1,
    "enhanced": 1,
    "enjoyed": 1,
    "enjoyment": 2,
    "enlarged": 3,
    "enlightened": 1,
    "enmity": 1,
    "enormities": 1,
    "enormous": 2,
    "enough": 2,
    "enquiries": 2,
    "enquiry": 4,
    "enter": 1,
    "entering": 1,
    "entertained": 1,
    "enthusiasm": 1,
    "entirely": 1,
    "entitle": 1,
    "entitled": 2,
    "epithet": 1,
    "equally": 1,
    "equitable": 2,
    "equivalent": 1,
    "erictho": 1,
    "errors": 1,
    "escape": 1,
    "escaped": 1,
    "especial": 1,
    "especially": 2,
    "essences": 1,
    "essex": 1,
    "establish": 1,
    "established": 1,
    "esteem": 1,
    "esteemed": 5,
    "esthonia": 1,
    "estimation": 1,
    "et": 1,
    "europe": 5,
    "european": 5,
    "europeans": 3,
    "eve": 1,
    "even": 10,
    "event": 2,
    "events": 2,
    "ever": 3,
    "every": 7,
    "evidence": 4,
    "evident": 2,
    "evil": 19,
    "evils": 1,
    "evoked": 1,
    "exact": 3,
    "example": 2,
    "examples": 1,
    "exchange": 1,
    "exchanged": 2,
    "excited": 1,
    "exclaimed": 1,
    "excluded": 1,
    "exclusively": 3,
    "excused": 1,
    "executed": 1,
    "execution": 1,
    "exercised": 1,
    "exercising": 1,
    "exert": 1,
    "exertion": 1,
    "exhibited": 4,
    "exhibition": 2,
    "exhibits": 1,
    "exist": 1,
    "existed": 6,
    "existence": 7,
    "exodus": 2,
    "expected": 1,
    "explain": 1,
    "explained": 1,
    "explaining": 1,
    "explanation": 1,
    "exploits": 1,
    "expose": 1,
    "exposition": 1,
    "expressed": 3,
    "expressions": 1,
    "expressly": 2,
    "expulsion": 1,
    "extend": 1,
    "extent": 4,
    "external": 1,
    "extracted": 1,
    "extraneous": 1,
    "extraordinary": 1,
    "extravagances": 2,
    "extreme": 3,
    "eye": 1,
    "eyes": 1,
    "eyewitness": 1,
    "ezekiel": 1,
    "fabulous": 1,
    "face": 3,
    "facilitate": 1,
    "fact": 5,
    "facts": 1,
    "faith": 15,
    "faithful": 1,
    "fall": 2,
    "fallacious": 1,
    "fallen": 3,
    "false": 5,
    "fame": 1,
    "familiar": 5,
    "familiarity": 2,
    "familiars": 1,
    "family": 1,
    "famous": 1,
    "fancy": 1,
    "far": 8,
    "farce": 1,
    "fast": 1,
    "fatal": 2,
    "fathers": 4,
    "favoured": 3,
    "feats": 1,
    "feeble": 1,
    "feel": 1,
    "feeling": 1,
    "feelings": 1,
    "feet": 1,
    "fell": 3,
    "female": 1,
    "females": 1,
    "fiction": 1,
    "fictions": 1,
    "fictitious": 1,
    "fiend": 1,
    "fiendhorse": 1,
    "fiends": 7,
    "figure": 2,
    "finally": 1,
    "find": 2,
    "fire": 4,
    "first": 5,
    "fish": 1,
    "fit": 1,
    "flagrant": 1,
    "flamens": 1,
    "fled": 1,
    "flesh": 3,
    "flight": 1,
    "flood": 3,
    "floodwizards": 1,
    "flowerinwoven": 1,
    "foal": 3,
    "followed": 1,
    "followers": 1,
    "foot": 3,
    "footnote": 4,
    "forbid": 1,
    "forbidden": 2,
    "force": 1,
    "ford": 1,
    "foregoes": 1,
    "forfeited": 1,
    "form": 1,
    "forman": 1,
    "formed": 1,
    "former": 2,
    "formerly": 1,
    "forms": 1,
    "forsake": 2,
    "forth": 1,
    "fortnight": 1,
    "fortune": 1,
    "fortuneteller": 3,
    "foulest": 1,
    "found": 6,
    "founded": 5,
    "founder": 2,
    "four": 1,
    "fourthly": 1,
    "frail": 1,
    "frame": 1,
    "fraternal": 1,
    "freed": 1,
    "freely": 1,
    "french": 1,
    "frenchmen": 2,
    "frequent": 2,
    "frequently": 2,
    "fresh": 1,
    "friend": 1,
    "fruit": 1,
    "fruitless": 1,
    "fruits": 1,
    "fulfilment": 2,
    "full": 1,
    "fully": 1,
    "fulness": 1,
    "fumes": 1,
    "fundamental": 1,
    "furclad": 1,
    "furnace": 1,
    "furnishing": 1,
    "future": 5,
    "futurity": 1,
    "gallant": 1,
    "gallows": 2,
    "garners": 1,
    "gather": 1,
    "gathered": 1,
    "gave": 4,
    "general": 8,
    "genius": 2,
    "gentile": 1,
    "genuine": 1,
    "george": 1,
    "germans": 1,
    "get": 1,
    "gibb": 5,
    "gibbites": 1,
    "gift": 1,
    "girt": 1,
    "give": 5,
    "given": 5,
    "globe": 1,
    "glory": 1,
    "gloucester": 1,
    "go": 2,
    "god": 15,
    "godly": 1,
    "gods": 14,
    "gone": 1,
    "good": 6,
    "goods": 3,
    "gore": 1,
    "gospel": 3,
    "gospels": 2,
    "gothic": 1,
    "government": 1,
    "governor": 1,
    "grace": 1,
    "gradually": 3,
    "grand": 1,
    "granted": 3,
    "gratification": 1,
    "grave": 2,
    "graver": 1,
    "great": 10,
    "greater": 2,
    "greatly": 2,
    "greece": 1,
    "grief": 1,
    "grisly": 1,
    "gross": 1,
    "grossness": 1,
    "ground": 1,
    "guards": 1,
    "guest": 1,
    "guilt": 2,
    "guilty": 1,
    "habitation": 1,
    "hags": 1,
    "hails": 1,
    "hammon": 1,
    "hand": 5,
    "hands": 2,
    "happily": 1,
    "hardened": 1,
    "hardly": 2,
    "harm": 1,
    "haste": 1,
    "hath": 2,
    "haunted": 1,
    "head": 2,
    "headed": 1,
    "hear": 1,
    "heard": 1,
    "hearers": 1,
    "hearing": 1,
    "hears": 1,
    "heart": 4,
    "hearth": 1,
    "heathen": 14,
    "heathendom": 1,
    "heathens": 6,
    "heaven": 2,
    "heavens": 1,
    "hebrew": 4,
    "hebrews": 1,
    "heir": 1,
    "held": 1,
    "hell": 1,
    "hellshould": 1,
    "help": 2,
    "herbs": 1,
    "herds": 1,
    "heretic": 1,
    "hidden": 1,
    "hideous": 2,
    "hieroglyphical": 1,
    "high": 1,
    "higher": 2,
    "highly": 3,
    "history": 7,
    "hitherto": 1,
    "hold": 2,
    "hollow": 1,
    "holy": 12,
    "homage": 4,
    "home": 1,
    "honest": 1,
    "honour": 1,
    "honoured": 1,
    "honouring": 1,
    "hoped": 1,
    "horn": 1,
    "horrible": 2,
    "horrors": 1,
    "horsejockey": 1,
    "horses": 1,
    "house": 1,
    "however": 10,
    "howling": 2,
    "hue": 1,
    "hum": 1,
    "human": 10,
    "humanity": 1,
    "hurt": 1,
    "husband": 1,
    "hypothesis": 1,
    "idea": 1,
    "ideas": 3,
    "identified": 1,
    "identifies": 1,
    "identifying": 1,
    "idol": 2,
    "idolatry": 2,
    "idols": 7,
    "ignorance": 5,
    "ignorant": 5,
    "ii": 2,
    "iithere": 1,
    "illustrate": 1,
    "illwill": 1,
    "image": 3,
    "images": 2,
    "imaginary": 2,
    "imitated": 1,
    "immediate": 3,
    "immediately": 2,
    "immense": 1,
    "immortality": 1,
    "imperfect": 2,
    "implied": 1,
    "implying": 1,
    "important": 3,
    "imposed": 2,
    "imposing": 1,
    "impositions": 1,
    "impossible": 4,
    "impostor": 1,
    "impostorby": 1,
    "impostors": 2,
    "imposture": 2,
    "impostureopinion": 1,
    "impotence": 1,
    "improbable": 2,
    "impudence": 1,
    "imputed": 1,
    "inappreciable": 1,
    "incalculable": 1,
    "incarnate": 1,
    "incarnation": 1,
    "incident": 2,
    "inclines": 1,
    "inconsistency": 1,
    "inconsistent": 3,
    "inconvenient": 1,
    "incredulity": 1,
    "inculcated": 1,
    "incur": 1,
    "indeed": 9,
    "india": 1,
    "indian": 1,
    "indians": 5,
    "indicate": 1,
    "indicating": 1,
    "indictment": 1,
    "indisputable": 1,
    "induced": 1,
    "indulgence": 1,
    "ineffectual": 1,
    "infecting": 1,
    "infer": 4,
    "inferior": 2,
    "inferiority": 1,
    "infernal": 5,
    "inferred": 1,
    "inflict": 1,
    "inflicted": 2,
    "infliction": 1,
    "influence": 6,
    "inform": 2,
    "information": 2,
    "informed": 1,
    "ingenious": 1,
    "ingratitude": 1,
    "inhabitant": 1,
    "inhabitants": 2,
    "iniquities": 1,
    "innocent": 1,
    "innoxious": 1,
    "innumerable": 1,
    "inserted": 1,
    "inspiration": 1,
    "inspired": 1,
    "inspires": 1,
    "inspiring": 1,
    "instance": 4,
    "instances": 1,
    "instead": 1,
    "instructed": 1,
    "instruction": 1,
    "instrument": 2,
    "instruments": 1,
    "insufficient": 1,
    "intellect": 1,
    "intelligence": 1,
    "intended": 4,
    "interalliance": 1,
    "intercessions": 1,
    "intercourse": 3,
    "interested": 1,
    "interesting": 1,
    "interference": 1,
    "interpretation": 1,
    "interpreted": 2,
    "intervention": 2,
    "interview": 2,
    "intimacy": 1,
    "intimate": 3,
    "intimated": 3,
    "intimates": 1,
    "introduced": 1,
    "intruding": 1,
    "invaluable": 1,
    "invisible": 2,
    "invocation": 1,
    "invocations": 2,
    "involve": 1,
    "involved": 2,
    "isaiah": 2,
    "isis": 1,
    "israel": 3,
    "israelites": 3,
    "itthe": 1,
    "jackson": 1,
    "jacob": 1,
    "jacsimiles": 1,
    "jail": 1,
    "jamie": 1,
    "jealous": 1,
    "jehovah": 1,
    "jehovahs": 1,
    "jesus": 1,
    "jew": 1,
    "jewish": 3,
    "jews": 5,
    "job": 1,
    "jobthe": 1,
    "joel": 1,
    "john": 4,
    "join": 1,
    "joined": 1,
    "jonsons": 1,
    "judges": 1,
    "judgment": 2,
    "judgments": 2,
    "judicial": 1,
    "jugglery": 2,
    "juggling": 3,
    "jupiter": 1,
    "justified": 1,
    "justly": 1,
    "juxtaposition": 1,
    "kept": 1,
    "killed": 2,
    "kind": 2,
    "kindness": 2,
    "kindred": 1,
    "king": 11,
    "kingdom": 2,
    "kneel": 1,
    "knees": 1,
    "knights": 1,
    "know": 4,
    "knowledge": 8,
    "known": 4,
    "lady": 1,
    "laid": 1,
    "lament": 1,
    "land": 4,
    "lapse": 1,
    "largely": 1,
    "lars": 1,
    "lastly": 1,
    "lately": 2,
    "later": 2,
    "latin": 1,
    "latter": 5,
    "law": 11,
    "lawbooks": 1,
    "laws": 4,
    "league": 2,
    "leagued": 1,
    "leagues": 1,
    "learn": 1,
    "learned": 4,
    "least": 2,
    "leave": 2,
    "leaving": 2,
    "left": 7,
    "legend": 2,
    "legends": 2,
    "legerdemain": 3,
    "legislate": 1,
    "legislator": 1,
    "lemures": 1,
    "length": 3,
    "lengths": 1,
    "lenity": 1,
    "less": 5,
    "lesser": 1,
    "lesson": 2,
    "let": 1,
    "levitical": 3,
    "leviticus": 1,
    "liable": 3,
    "liableto": 1,
    "liberal": 1,
    "liberty": 4,
    "license": 1,
    "life": 4,
    "light": 2,
    "lightly": 1,
    "like": 15,
    "likely": 4,
    "likeness": 3,
    "limb": 1,
    "limitation": 1,
    "limited": 1,
    "limits": 2,
    "linger": 1,
    "lion": 2,
    "literally": 2,
    "lithuania": 1,
    "little": 6,
    "live": 1,
    "lived": 1,
    "liver": 1,
    "lives": 1,
    "locks": 1,
    "logs": 1,
    "lonely": 1,
    "long": 2,
    "longer": 2,
    "longevity": 1,
    "lord": 2,
    "lords": 1,
    "loss": 1,
    "lost": 1,
    "loud": 2,
    "lower": 3,
    "luke": 1,
    "lump": 1,
    "lunatic": 1,
    "lybic": 1,
    "lying": 3,
    "mad": 1,
    "made": 7,
    "madman": 1,
    "magi": 1,
    "magic": 2,
    "magician": 1,
    "magiciansarticles": 1,
    "magnalia": 2,
    "magnitude": 1,
    "magus": 2,
    "mahommedan": 1,
    "mahommedans": 2,
    "mahound": 1,
    "maids": 1,
    "make": 2,
    "maker": 2,
    "maketh": 1,
    "malignant": 2,
    "man": 11,
    "manasses": 1,
    "mandate": 1,
    "maniac": 2,
    "manifest": 1,
    "manifestation": 2,
    "manifestations": 3,
    "mankind": 6,
    "manner": 8,
    "manners": 1,
    "mantle": 1,
    "many": 12,
    "maps": 1,
    "marble": 1,
    "mare": 4,
    "marks": 3,
    "mars": 1,
    "marvels": 1,
    "mass": 1,
    "match": 1,
    "mather": 2,
    "mathergibb": 1,
    "matter": 1,
    "may": 27,
    "mean": 4,
    "meaner": 1,
    "meaning": 1,
    "means": 8,
    "meant": 1,
    "meantime": 1,
    "medical": 1,
    "medicator": 1,
    "meet": 2,
    "meeting": 1,
    "meikle": 2,
    "melancholy": 2,
    "members": 1,
    "memorable": 2,
    "men": 15,
    "menit": 1,
    "mens": 1,
    "mention": 3,
    "mentioned": 3,
    "mentions": 1,
    "mercies": 1,
    "mere": 6,
    "merely": 3,
    "messenger": 1,
    "metaphorically": 1,
    "mexicans": 1,
    "mexico": 2,
    "middle": 6,
    "midnight": 1,
    "midst": 1,
    "might": 23,
    "miles": 1,
    "military": 1,
    "milton": 3,
    "miltoncases": 1,
    "mind": 2,
    "minds": 3,
    "minerva": 1,
    "ministry": 1,
    "minutely": 1,
    "minuti\u00e6": 1,
    "miracles": 9,
    "miraclesopinion": 1,
    "miraculous": 4,
    "miraculously": 1,
    "mischief": 1,
    "miserable": 1,
    "misfortune": 2,
    "mission": 4,
    "mistaken": 1,
    "misunderstood": 1,
    "mixture": 1,
    "moan": 1,
    "mode": 1,
    "modern": 8,
    "molestation": 1,
    "moloch": 1,
    "monarchs": 1,
    "mooned": 1,
    "moorlands": 1,
    "moral": 1,
    "moreover": 1,
    "mortality": 2,
    "mortals": 6,
    "mosaic": 4,
    "moses": 5,
    "moss": 1,
    "mother": 1,
    "mountains": 1,
    "mounted": 1,
    "mourn": 2,
    "mouth": 2,
    "mouths": 1,
    "much": 13,
    "murder": 1,
    "murmuring": 1,
    "museum": 1,
    "must": 12,
    "mystical": 2,
    "mythology": 3,
    "nahas": 1,
    "name": 4,
    "names": 1,
    "napkin": 2,
    "narrative": 2,
    "narrowly": 1,
    "nation": 1,
    "nations": 9,
    "native": 3,
    "natives": 4,
    "nativity": 2,
    "natural": 2,
    "naturally": 2,
    "nature": 13,
    "nearly": 1,
    "necessarily": 2,
    "necessary": 6,
    "necessity": 1,
    "necromancer": 1,
    "neighbourhood": 1,
    "neighbouring": 2,
    "neighbours": 2,
    "neighed": 2,
    "neither": 4,
    "never": 2,
    "nevertheless": 3,
    "new": 6,
    "nightly": 1,
    "nile": 1,
    "nineteenth": 1,
    "nobly": 1,
    "north": 5,
    "northern": 2,
    "note": 1,
    "nothing": 1,
    "noticed": 2,
    "notices": 1,
    "notions": 1,
    "notwithstanding": 4,
    "noxious": 1,
    "number": 1,
    "numberless": 1,
    "numerous": 1,
    "nuptial": 2,
    "nymphs": 1,
    "obedience": 2,
    "obedient": 1,
    "obey": 1,
    "obeying": 1,
    "object": 4,
    "objection": 2,
    "objections": 1,
    "objects": 1,
    "obliged": 1,
    "obscure": 1,
    "observant": 1,
    "observation": 2,
    "observe": 1,
    "observed": 3,
    "observer": 1,
    "observing": 1,
    "obtain": 4,
    "obtained": 5,
    "obtaining": 1,
    "occasion": 3,
    "occasional": 2,
    "occasionally": 3,
    "occasioned": 1,
    "occupying": 1,
    "occur": 2,
    "occurred": 3,
    "occurs": 4,
    "odious": 1,
    "oer": 1,
    "offence": 2,
    "offences": 2,
    "offended": 2,
    "offenders": 1,
    "offering": 1,
    "officers": 2,
    "often": 4,
    "old": 8,
    "omnipotence": 1,
    "one": 16,
    "open": 2,
    "openly": 2,
    "operated": 1,
    "opinion": 6,
    "opinions": 2,
    "oracle": 2,
    "oracles": 7,
    "order": 2,
    "ordinary": 2,
    "organs": 1,
    "origin": 1,
    "original": 1,
    "originally": 2,
    "orus": 1,
    "others": 5,
    "otherwise": 3,
    "ought": 1,
    "outlines": 1,
    "outrages": 1,
    "outright": 1,
    "overbury": 1,
    "overcome": 1,
    "owe": 1,
    "owned": 1,
    "p": 1,
    "pagan": 6,
    "paganismand": 1,
    "pagans": 2,
    "paid": 2,
    "painted": 1,
    "pale": 2,
    "paleeyed": 1,
    "palestine": 2,
    "palterd": 1,
    "paltry": 1,
    "panicthe": 1,
    "panto": 1,
    "paradise": 1,
    "parents": 2,
    "part": 16,
    "particular": 6,
    "particularly": 2,
    "parting": 1,
    "parts": 3,
    "party": 2,
    "pass": 3,
    "passage": 6,
    "passages": 2,
    "passed": 1,
    "passions": 1,
    "path": 1,
    "patrick": 1,
    "patron": 1,
    "patronage": 1,
    "paul": 1,
    "pausing": 1,
    "paying": 1,
    "peculiar": 4,
    "people": 12,
    "peor": 1,
    "perfect": 1,
    "perfected": 1,
    "perform": 1,
    "perhaps": 2,
    "period": 11,
    "periodand": 1,
    "permission": 5,
    "permitted": 10,
    "persecuted": 1,
    "persecution": 2,
    "persecutors": 1,
    "person": 8,
    "personal": 1,
    "personally": 2,
    "personifications": 2,
    "persons": 5,
    "peru": 1,
    "perversion": 2,
    "perverting": 1,
    "pestilence": 1,
    "peter": 2,
    "petty": 1,
    "phantasmagoria": 1,
    "pharaoh": 1,
    "pharaohtext": 1,
    "philistines": 1,
    "phipps": 1,
    "phrase": 1,
    "pieces": 2,
    "place": 6,
    "placed": 1,
    "places": 2,
    "plagued": 1,
    "plagues": 1,
    "plain": 1,
    "plainest": 1,
    "plaint": 1,
    "planisphere": 1,
    "play": 1,
    "played": 1,
    "plead": 1,
    "pleased": 2,
    "pleasure": 5,
    "poet": 1,
    "poetry": 2,
    "points": 1,
    "pointthat": 1,
    "poison": 2,
    "poisoner": 2,
    "poisoneror": 1,
    "poisons": 2,
    "poor": 2,
    "poplar": 1,
    "popular": 2,
    "portents": 1,
    "portion": 1,
    "portuguese": 2,
    "position": 1,
    "positionsa": 1,
    "possessed": 5,
    "possessing": 3,
    "possession": 5,
    "possessions": 1,
    "possessor": 1,
    "possibility": 5,
    "possible": 4,
    "potions": 1,
    "pour": 1,
    "pourtrayed": 1,
    "powah": 3,
    "powahing": 1,
    "powahs": 7,
    "power": 30,
    "powerful": 2,
    "powers": 6,
    "practice": 4,
    "practices": 5,
    "practise": 2,
    "practised": 2,
    "practising": 1,
    "prayed": 1,
    "praying": 1,
    "preceded": 1,
    "precedence": 1,
    "precise": 2,
    "precisely": 1,
    "preconcerted": 1,
    "prediction": 1,
    "predictions": 1,
    "preferred": 1,
    "prelacy": 1,
    "premeditated": 1,
    "premising": 1,
    "preparing": 1,
    "presbyteriana": 1,
    "presence": 2,
    "present": 5,
    "presenting": 1,
    "preserve": 1,
    "preserved": 1,
    "presided": 1,
    "presume": 2,
    "presumptuous": 1,
    "pretended": 4,
    "pretensions": 3,
    "pretty": 1,
    "prevailing": 1,
    "prevented": 2,
    "previously": 2,
    "price": 1,
    "pride": 1,
    "priesthood": 1,
    "priests": 6,
    "prince": 2,
    "princess": 1,
    "principal": 1,
    "principles": 1,
    "prison": 1,
    "prisoners": 2,
    "privilege": 1,
    "privileges": 1,
    "probability": 2,
    "probable": 2,
    "probably": 3,
    "probe": 1,
    "proceeded": 1,
    "proceeds": 1,
    "produce": 2,
    "produced": 4,
    "produceresumption": 1,
    "profane": 2,
    "professed": 1,
    "profession": 2,
    "professionally": 1,
    "progress": 1,
    "prohibited": 2,
    "prohibitions": 1,
    "promise": 2,
    "promises": 1,
    "pronounce": 2,
    "proof": 2,
    "proofs": 2,
    "proper": 1,
    "property": 1,
    "prophecies": 2,
    "prophesied": 1,
    "prophesy": 2,
    "prophet": 7,
    "prophetand": 1,
    "prophetess": 1,
    "prophetic": 1,
    "prophets": 7,
    "proportion": 1,
    "proposal": 2,
    "proposition": 2,
    "prose": 1,
    "prosecution": 1,
    "protect": 1,
    "protection": 1,
    "protest": 1,
    "protestant": 1,
    "protestants": 2,
    "prove": 3,
    "proved": 3,
    "proves": 1,
    "providence": 4,
    "public": 2,
    "published": 1,
    "punish": 1,
    "punished": 3,
    "punishment": 9,
    "purchase": 1,
    "purpose": 5,
    "purposes": 2,
    "pursue": 1,
    "put": 2,
    "pythoness": 4,
    "quaint": 1,
    "qualified": 1,
    "queen": 1,
    "question": 5,
    "questions": 1,
    "quieting": 1,
    "quotation": 1,
    "quoted": 1,
    "race": 5,
    "raise": 3,
    "raising": 2,
    "ran": 1,
    "rank": 6,
    "ranked": 1,
    "ransomed": 1,
    "rarer": 1,
    "rate": 1,
    "rather": 3,
    "ravage": 1,
    "read": 1,
    "reader": 3,
    "readers": 1,
    "real": 10,
    "really": 2,
    "reason": 2,
    "reasonably": 1,
    "rebellion": 1,
    "receive": 1,
    "received": 3,
    "recent": 1,
    "reception": 1,
    "recognises": 1,
    "recommend": 1,
    "recommended": 2,
    "records": 1,
    "recourse": 3,
    "refer": 1,
    "reflect": 1,
    "refuse": 2,
    "regiments": 1,
    "regions": 1,
    "regular": 1,
    "regularly": 1,
    "reinforcement": 1,
    "reiterating": 1,
    "rejected": 1,
    "related": 1,
    "religion": 6,
    "religious": 1,
    "remain": 1,
    "remains": 3,
    "remark": 1,
    "remarkable": 5,
    "remarked": 1,
    "remarks": 1,
    "removed": 2,
    "removes": 1,
    "removing": 1,
    "rendered": 3,
    "renowned": 1,
    "repeated": 1,
    "repeatedly": 3,
    "repetition": 1,
    "replenishing": 1,
    "reports": 2,
    "repose": 1,
    "reposed": 1,
    "represented": 2,
    "representing": 1,
    "reproach": 1,
    "requested": 1,
    "requirethat": 1,
    "requiring": 1,
    "resemblance": 2,
    "resemblanceor": 1,
    "resembled": 1,
    "resembling": 2,
    "resolved": 1,
    "resolves": 1,
    "resorted": 4,
    "resorting": 2,
    "resounding": 1,
    "respect": 4,
    "respecting": 3,
    "response": 1,
    "responses": 2,
    "rest": 2,
    "rested": 1,
    "restingplace": 1,
    "restrained": 3,
    "restraint": 1,
    "return": 1,
    "returning": 1,
    "revelation": 2,
    "revelations": 1,
    "revellings": 1,
    "revelry": 1,
    "revels": 1,
    "reverence": 3,
    "reverenced": 1,
    "reverend": 1,
    "review": 1,
    "richard": 4,
    "rider": 1,
    "ridicule": 1,
    "ridiculous": 1,
    "ring": 1,
    "rites": 2,
    "ritual": 1,
    "rode": 1,
    "rods": 1,
    "roman": 2,
    "romance": 3,
    "romances": 1,
    "romans": 1,
    "romantic": 1,
    "rome": 1,
    "roof": 1,
    "rooted": 1,
    "round": 1,
    "rude": 1,
    "ruins": 1,
    "ruler": 2,
    "runs": 1,
    "sacred": 4,
    "sacrifices": 3,
    "safely": 3,
    "said": 7,
    "saint": 1,
    "saints": 1,
    "saladin": 3,
    "samuel": 9,
    "samuels": 2,
    "sanction": 1,
    "sanctioned": 1,
    "saracen": 1,
    "saracens": 3,
    "sat": 1,
    "satan": 8,
    "satisfactory": 1,
    "saucer": 1,
    "saul": 8,
    "saulsupposed": 1,
    "save": 1,
    "saviour": 5,
    "savours": 1,
    "saw": 1,
    "say": 1,
    "says": 2,
    "scale": 1,
    "scalped": 1,
    "scandal": 1,
    "scandalous": 1,
    "scarce": 1,
    "scarcely": 1,
    "scene": 1,
    "scimitars": 1,
    "scottish": 1,
    "scriptural": 1,
    "scripture": 9,
    "scriptures": 3,
    "sculptor": 1,
    "seat": 1,
    "second": 3,
    "secondly": 1,
    "secrets": 2,
    "see": 3,
    "seem": 2,
    "seemed": 1,
    "seeming": 1,
    "seemingly": 2,
    "seems": 7,
    "seers": 1,
    "selected": 1,
    "sense": 12,
    "senseless": 2,
    "senses": 2,
    "sent": 2,
    "sentence": 1,
    "separate": 1,
    "separated": 2,
    "septuagint": 1,
    "seq": 1,
    "serpents": 2,
    "servant": 2,
    "served": 2,
    "service": 2,
    "settlement": 1,
    "settlers": 3,
    "seven": 1,
    "several": 1,
    "severally": 1,
    "severe": 1,
    "severely": 1,
    "severities": 1,
    "severity": 1,
    "shade": 1,
    "shadows": 1,
    "shall": 2,
    "shamed": 1,
    "shape": 2,
    "shapes": 1,
    "share": 1,
    "sheer": 1,
    "shield": 1,
    "shine": 1,
    "shipmaster": 1,
    "shocking": 1,
    "shook": 1,
    "shore": 1,
    "short": 1,
    "shorten": 1,
    "shortened": 1,
    "show": 2,
    "showed": 4,
    "showing": 1,
    "shriek": 1,
    "shrine": 1,
    "shrines": 1,
    "shrinks": 1,
    "sift": 1,
    "sighing": 1,
    "sign": 3,
    "signal": 2,
    "signified": 1,
    "silence": 2,
    "silenced": 3,
    "similar": 11,
    "simon": 2,
    "simple": 1,
    "sin": 3,
    "since": 10,
    "sinful": 2,
    "single": 1,
    "sinking": 1,
    "sins": 2,
    "sir": 2,
    "sits": 1,
    "sixteenth": 1,
    "size": 2,
    "skilful": 1,
    "skill": 4,
    "skirmished": 1,
    "slaves": 1,
    "sleep": 2,
    "slighter": 1,
    "slightest": 1,
    "snakegod": 1,
    "snaky": 1,
    "snares": 1,
    "soldan": 2,
    "soldier": 1,
    "soldiers": 1,
    "solemn": 1,
    "solution": 1,
    "something": 4,
    "sometimes": 1,
    "son": 1,
    "sons": 2,
    "soon": 2,
    "soothsayers": 1,
    "sorcerer": 4,
    "sorcerers": 2,
    "sorceress": 3,
    "sorceries": 1,
    "sorcery": 3,
    "sortilege": 1,
    "sound": 1,
    "source": 1,
    "sourcelegerdemain": 1,
    "sources": 1,
    "south": 1,
    "space": 1,
    "spaniards": 1,
    "speak": 1,
    "speaking": 1,
    "species": 4,
    "specific": 1,
    "specimen": 1,
    "spectators": 1,
    "speculation": 1,
    "spell": 1,
    "spells": 1,
    "spirit": 13,
    "spirits": 19,
    "spiritsbut": 1,
    "spiritswe": 1,
    "spiritual": 6,
    "spite": 1,
    "splendid": 1,
    "spot": 1,
    "spread": 2,
    "spreading": 1,
    "spring": 1,
    "st": 2,
    "stamp": 1,
    "startling": 1,
    "state": 2,
    "statement": 1,
    "steep": 1,
    "step": 1,
    "stephen": 1,
    "still": 5,
    "stirling": 1,
    "stocks": 1,
    "stolen": 2,
    "stones": 1,
    "stopped": 1,
    "stories": 1,
    "storm": 1,
    "story": 1,
    "strain": 1,
    "strangled": 1,
    "stratagem": 3,
    "straying": 1,
    "strength": 1,
    "stress": 1,
    "strictly": 1,
    "striking": 2,
    "strong": 1,
    "stronger": 1,
    "struck": 1,
    "studies": 1,
    "style": 1,
    "subject": 5,
    "subjection": 1,
    "subjects": 2,
    "submission": 1,
    "subsequent": 1,
    "subservient": 1,
    "substituted": 2,
    "success": 1,
    "successful": 1,
    "successfully": 1,
    "succession": 1,
    "successors": 1,
    "suchwould": 1,
    "suck": 1,
    "sucking": 1,
    "suffer": 2,
    "suffered": 6,
    "suffering": 1,
    "sufficiently": 3,
    "sullen": 1,
    "summons": 1,
    "superior": 5,
    "superiority": 2,
    "supernatural": 10,
    "superstition": 2,
    "superstitions": 1,
    "superstitious": 3,
    "support": 3,
    "suppose": 4,
    "supposed": 10,
    "supposes": 1,
    "supposing": 6,
    "suppositions": 1,
    "supremacy": 1,
    "supremacyother": 1,
    "supreme": 3,
    "sure": 1,
    "surely": 1,
    "surprise": 2,
    "surrounded": 1,
    "survive": 1,
    "survived": 1,
    "suspended": 2,
    "suspicion": 1,
    "sway": 1,
    "sweat": 1,
    "swerving": 1,
    "synonymous": 1,
    "system": 8,
    "systemalso": 1,
    "table": 1,
    "tail": 1,
    "take": 2,
    "taken": 1,
    "taking": 1,
    "tale": 3,
    "talents": 1,
    "tangled": 1,
    "tapers": 1,
    "task": 1,
    "tell": 1,
    "temperament": 1,
    "tempests": 2,
    "temples": 1,
    "temptation": 2,
    "tempted": 1,
    "tenanted": 1,
    "tendency": 1,
    "tenet": 1,
    "tenor": 1,
    "teraphim": 1,
    "term": 2,
    "termagaunt": 1,
    "termed": 2,
    "terror": 1,
    "testament": 7,
    "teutonic": 1,
    "text": 5,
    "texts": 3,
    "th": 3,
    "thammuz": 1,
    "thatthough": 1,
    "theological": 1,
    "theory": 1,
    "therefore": 7,
    "thickets": 1,
    "thing": 1,
    "things": 2,
    "think": 1,
    "thirdly": 1,
    "thirty": 1,
    "thomas": 2,
    "though": 12,
    "thought": 2,
    "thousandth": 1,
    "thrust": 1,
    "thummim": 1,
    "thus": 6,
    "till": 3,
    "time": 10,
    "times": 6,
    "tinged": 1,
    "title": 2,
    "tobit": 1,
    "token": 1,
    "told": 3,
    "tolerant": 1,
    "toleration": 1,
    "tone": 1,
    "took": 4,
    "tormented": 1,
    "tormenting": 1,
    "torn": 1,
    "toturity": 1,
    "touch": 1,
    "town": 1,
    "trace": 2,
    "traces": 1,
    "tradition": 1,
    "traffic": 2,
    "trafficking": 1,
    "tragedy": 1,
    "train": 1,
    "trance": 1,
    "transaction": 1,
    "transferring": 1,
    "transform": 1,
    "transforming": 1,
    "transgression": 1,
    "translated": 1,
    "transported": 1,
    "treason": 1,
    "treated": 1,
    "tree": 2,
    "tresses": 2,
    "trial": 1,
    "trick": 3,
    "tricks": 2,
    "true": 6,
    "truth": 2,
    "try": 2,
    "turks": 1,
    "turn": 1,
    "twentieth": 1,
    "twenty": 1,
    "twentysecond": 1,
    "twicebattered": 1,
    "twilight": 1,
    "two": 7,
    "tyrant": 1,
    "tyrian": 1,
    "ultimate": 1,
    "unable": 1,
    "unavailing": 3,
    "uncertain": 2,
    "uncommon": 1,
    "unconvertedthe": 1,
    "undeniable": 1,
    "understand": 4,
    "understanddarkly": 1,
    "understanding": 1,
    "understood": 3,
    "undoubtedly": 1,
    "unedifying": 1,
    "unequalled": 1,
    "unexpected": 1,
    "unfortunate": 2,
    "ungrateful": 1,
    "unhappy": 1,
    "uniformly": 1,
    "union": 1,
    "unique": 1,
    "unitarian": 1,
    "universal": 1,
    "universally": 1,
    "universe": 1,
    "unknightly": 1,
    "unknown": 3,
    "unlawful": 1,
    "unlucky": 1,
    "unnatural": 3,
    "unpleasing": 1,
    "unquestionably": 1,
    "unrelenting": 1,
    "unworthy": 1,
    "upon": 25,
    "urim": 1,
    "urns": 1,
    "us": 15,
    "use": 3,
    "used": 3,
    "useth": 1,
    "using": 1,
    "usual": 1,
    "utility": 1,
    "uttering": 1,
    "utterly": 2,
    "uzzs": 1,
    "vain": 3,
    "varied": 1,
    "various": 3,
    "vassal": 1,
    "vassals": 1,
    "vehemence": 1,
    "veletri": 1,
    "veneficus": 1,
    "venial": 1,
    "venus": 1,
    "ver": 1,
    "verse": 2,
    "version": 1,
    "vex": 1,
    "vi": 1,
    "victims": 1,
    "victimwhereas": 1,
    "view": 1,
    "vii": 1,
    "vile": 1,
    "violation": 1,
    "virgin": 2,
    "virtue": 1,
    "visibly": 1,
    "visions": 1,
    "visitants": 1,
    "visited": 1,
    "voice": 3,
    "vol": 1,
    "volume": 1,
    "volumes": 1,
    "voyager": 1,
    "walker": 1,
    "walkers": 1,
    "wall": 1,
    "wanderers": 1,
    "want": 1,
    "warfare": 1,
    "warhorse": 1,
    "warlock": 1,
    "warned": 1,
    "warning": 1,
    "waste": 1,
    "wax": 2,
    "way": 3,
    "weapons": 1,
    "wear": 1,
    "wearing": 1,
    "weeping": 1,
    "weight": 1,
    "well": 5,
    "went": 1,
    "west": 1,
    "western": 1,
    "whatever": 3,
    "wheat": 1,
    "whence": 1,
    "whenever": 2,
    "wherefore": 1,
    "whether": 13,
    "whither": 1,
    "whole": 1,
    "whose": 6,
    "wicked": 2,
    "wider": 1,
    "wife": 1,
    "wilderness": 1,
    "wildest": 1,
    "william": 1,
    "willing": 1,
    "wings": 1,
    "wisdom": 1,
    "wise": 2,
    "witch": 30,
    "witchcraft": 23,
    "witchcraftthe": 1,
    "witches": 6,
    "witchesthe": 1,
    "witchexample": 1,
    "withdrawn": 2,
    "withholds": 1,
    "within": 3,
    "without": 6,
    "wizard": 3,
    "wizards": 4,
    "wizardsinstance": 1,
    "wodrows": 1,
    "woman": 7,
    "womanyet": 1,
    "wonder": 1,
    "wont": 1,
    "wonted": 1,
    "wood": 1,
    "word": 13,
    "words": 5,
    "work": 4,
    "working": 1,
    "world": 12,
    "worldeffects": 1,
    "worship": 14,
    "worshipped": 5,
    "worshipper": 1,
    "worshippers": 2,
    "worst": 1,
    "worsted": 1,
    "worthy": 1,
    "would": 9,
    "wounded": 1,
    "wounding": 1,
    "wreck": 1,
    "wretched": 1,
    "wretches": 1,
    "wring": 1,
    "writ": 1,
    "writers": 2,
    "writing": 1,
    "writings": 3,
    "written": 2,
    "wrought": 1,
    "x": 1,
    "xix": 1,
    "xlvi": 1,
    "xviii": 2,
    "xxii": 1,
    "xxxviii": 1,
    "year": 2,
    "years": 1,
    "yet": 8,
    "york": 1,
    "young": 1,
    "zeal": 1
}
